[{"stock":"gdx","expiry":"2024-11-08T00:00:00","stk_price":39.87,"em":2.18,"empct":0.052},{"stock":"gdx","expiry":"2024-11-15T00:00:00","stk_price":39.87,"em":2.59,"empct":0.062},{"stock":"gdx","expiry":"2024-11-22T00:00:00","stk_price":39.87,"em":3.09,"empct":0.074},{"stock":"gdx","expiry":"2024-11-29T00:00:00","stk_price":39.87,"em":3.37,"empct":0.08},{"stock":"gdx","expiry":"2024-12-06T00:00:00","stk_price":39.87,"em":3.94,"empct":0.094},{"stock":"gdx","expiry":"2024-12-13T00:00:00","stk_price":39.87,"em":3.95,"empct":0.094},{"stock":"gdx","expiry":"2024-12-20T00:00:00","stk_price":39.87,"em":1.87,"empct":0.045},{"stock":"gme","expiry":"2024-11-08T00:00:00","stk_price":22.24,"em":1.69,"empct":0.072},{"stock":"gme","expiry":"2024-11-15T00:00:00","stk_price":22.24,"em":2.47,"empct":0.106},{"stock":"gme","expiry":"2024-11-22T00:00:00","stk_price":22.24,"em":3.27,"empct":0.14},{"stock":"gme","expiry":"2024-11-29T00:00:00","stk_price":22.24,"em":3.62,"empct":0.155},{"stock":"gme","expiry":"2024-12-06T00:00:00","stk_price":22.24,"em":4.31,"empct":0.184},{"stock":"gme","expiry":"2024-12-13T00:00:00","stk_price":22.24,"em":5.35,"empct":0.229},{"stock":"gme","expiry":"2024-12-20T00:00:00","stk_price":22.24,"em":3.0,"empct":0.128},{"stock":"amzn","expiry":"2024-11-08T00:00:00","stk_price":195.99,"em":6.99,"empct":0.034},{"stock":"amzn","expiry":"2024-11-15T00:00:00","stk_price":195.99,"em":9.27,"empct":0.045},{"stock":"amzn","expiry":"2024-11-22T00:00:00","stk_price":195.99,"em":5.71,"empct":0.028},{"stock":"amzn","expiry":"2024-11-29T00:00:00","stk_price":195.99,"em":6.3,"empct":0.031},{"stock":"amzn","expiry":"2024-12-06T00:00:00","stk_price":195.99,"em":7.24,"empct":0.035},{"stock":"amzn","expiry":"2024-12-13T00:00:00","stk_price":195.99,"em":7.98,"empct":0.039},{"stock":"amzn","expiry":"2024-12-20T00:00:00","stk_price":195.99,"em":8.7,"empct":0.042},{"stock":"spy","expiry":"2024-11-05T00:00:00","stk_price":570.61,"em":4.55,"empct":0.008},{"stock":"spy","expiry":"2024-11-06T00:00:00","stk_price":570.61,"em":11.15,"empct":0.019},{"stock":"spy","expiry":"2024-11-07T00:00:00","stk_price":570.61,"em":13.12,"empct":0.022},{"stock":"spy","expiry":"2024-11-08T00:00:00","stk_price":570.61,"em":14.48,"empct":0.024},{"stock":"spy","expiry":"2024-11-11T00:00:00","stk_price":570.61,"em":15.28,"empct":0.025},{"stock":"spy","expiry":"2024-11-12T00:00:00","stk_price":570.61,"em":15.92,"empct":0.027},{"stock":"spy","expiry":"2024-11-13T00:00:00","stk_price":570.61,"em":16.86,"empct":0.028},{"stock":"spy","expiry":"2024-11-14T00:00:00","stk_price":570.61,"em":9.4,"empct":0.016},{"stock":"spy","expiry":"2024-11-15T00:00:00","stk_price":570.61,"em":18.04,"empct":0.03},{"stock":"spy","expiry":"2024-11-22T00:00:00","stk_price":570.61,"em":21.02,"empct":0.035},{"stock":"spy","expiry":"2024-11-29T00:00:00","stk_price":570.61,"em":22.71,"empct":0.038},{"stock":"spy","expiry":"2024-12-06T00:00:00","stk_price":570.61,"em":24.97,"empct":0.042},{"stock":"spy","expiry":"2024-12-13T00:00:00","stk_price":570.61,"em":26.91,"empct":0.045},{"stock":"spy","expiry":"2024-12-20T00:00:00","stk_price":570.61,"em":29.03,"empct":0.048},{"stock":"spy","expiry":"2024-12-31T00:00:00","stk_price":570.61,"em":30.67,"empct":0.051},{"stock":"xlf","expiry":"2024-11-08T00:00:00","stk_price":46.31,"em":1.8,"empct":0.037},{"stock":"xlf","expiry":"2024-11-15T00:00:00","stk_price":46.31,"em":2.02,"empct":0.041},{"stock":"xlf","expiry":"2024-11-22T00:00:00","stk_price":46.31,"em":2.3,"empct":0.047},{"stock":"xlf","expiry":"2024-11-29T00:00:00","stk_price":46.31,"em":2.25,"empct":0.046},{"stock":"xlf","expiry":"2024-12-06T00:00:00","stk_price":46.31,"em":2.21,"empct":0.045},{"stock":"xlf","expiry":"2024-12-13T00:00:00","stk_price":46.31,"em":1.0,"empct":0.021},{"stock":"xlf","expiry":"2024-12-20T00:00:00","stk_price":46.31,"em":1.65,"empct":0.034},{"stock":"xlf","expiry":"2024-12-31T00:00:00","stk_price":46.31,"em":1.87,"empct":0.038},{"stock":"aapl","expiry":"2024-11-08T00:00:00","stk_price":222.65,"em":7.22,"empct":0.031},{"stock":"aapl","expiry":"2024-11-15T00:00:00","stk_price":222.65,"em":9.35,"empct":0.04},{"stock":"aapl","expiry":"2024-11-22T00:00:00","stk_price":222.65,"em":5.99,"empct":0.026},{"stock":"aapl","expiry":"2024-11-29T00:00:00","stk_price":222.65,"em":6.53,"empct":0.028},{"stock":"aapl","expiry":"2024-12-06T00:00:00","stk_price":222.65,"em":7.15,"empct":0.031},{"stock":"aapl","expiry":"2024-12-13T00:00:00","stk_price":222.65,"em":8.4,"empct":0.036},{"stock":"aapl","expiry":"2024-12-20T00:00:00","stk_price":222.65,"em":8.08,"empct":0.034},{"stock":"pfe","expiry":"2024-11-08T00:00:00","stk_price":27.81,"em":1.29,"empct":0.044},{"stock":"pfe","expiry":"2024-11-15T00:00:00","stk_price":27.81,"em":1.52,"empct":0.052},{"stock":"pfe","expiry":"2024-11-22T00:00:00","stk_price":27.81,"em":0.92,"empct":0.031},{"stock":"pfe","expiry":"2024-11-29T00:00:00","stk_price":27.81,"em":1.01,"empct":0.035},{"stock":"pfe","expiry":"2024-12-06T00:00:00","stk_price":27.81,"em":1.04,"empct":0.036},{"stock":"pfe","expiry":"2024-12-13T00:00:00","stk_price":27.81,"em":1.16,"empct":0.04},{"stock":"pfe","expiry":"2024-12-20T00:00:00","stk_price":27.81,"em":1.21,"empct":0.041},{"stock":"aal","expiry":"2024-11-08T00:00:00","stk_price":13.16,"em":0.87,"empct":0.063},{"stock":"aal","expiry":"2024-11-15T00:00:00","stk_price":13.16,"em":1.24,"empct":0.09},{"stock":"aal","expiry":"2024-11-22T00:00:00","stk_price":13.16,"em":1.4,"empct":0.101},{"stock":"aal","expiry":"2024-11-29T00:00:00","stk_price":13.16,"em":1.49,"empct":0.108},{"stock":"aal","expiry":"2024-12-06T00:00:00","stk_price":13.16,"em":1.69,"empct":0.122},{"stock":"aal","expiry":"2024-12-13T00:00:00","stk_price":13.16,"em":1.78,"empct":0.128},{"stock":"aal","expiry":"2024-12-20T00:00:00","stk_price":13.16,"em":0.98,"empct":0.071},{"stock":"igv","expiry":"2024-11-08T00:00:00","stk_price":92.54,"em":2.23,"empct":0.023},{"stock":"igv","expiry":"2024-11-15T00:00:00","stk_price":92.54,"em":3.89,"empct":0.04},{"stock":"uber","expiry":"2024-11-08T00:00:00","stk_price":73.5,"em":3.41,"empct":0.044},{"stock":"uber","expiry":"2024-11-15T00:00:00","stk_price":73.5,"em":4.38,"empct":0.057},{"stock":"uber","expiry":"2024-11-22T00:00:00","stk_price":73.5,"em":5.17,"empct":0.067},{"stock":"uber","expiry":"2024-11-29T00:00:00","stk_price":73.5,"em":5.82,"empct":0.075},{"stock":"uber","expiry":"2024-12-06T00:00:00","stk_price":73.5,"em":7.59,"empct":0.098},{"stock":"uber","expiry":"2024-12-13T00:00:00","stk_price":73.5,"em":7.1,"empct":0.092},{"stock":"xli","expiry":"2024-11-08T00:00:00","stk_price":133.99,"em":3.85,"empct":0.027},{"stock":"xli","expiry":"2024-11-15T00:00:00","stk_price":133.99,"em":2.13,"empct":0.015},{"stock":"xli","expiry":"2024-11-22T00:00:00","stk_price":133.99,"em":1.82,"empct":0.013},{"stock":"xli","expiry":"2024-11-29T00:00:00","stk_price":133.99,"em":2.6,"empct":0.018},{"stock":"xli","expiry":"2024-12-06T00:00:00","stk_price":133.99,"em":2.78,"empct":0.02},{"stock":"xli","expiry":"2024-12-20T00:00:00","stk_price":133.99,"em":3.28,"empct":0.023},{"stock":"uup","expiry":"2024-11-15T00:00:00","stk_price":29.2,"em":1.32,"empct":0.043},{"stock":"uup","expiry":"2024-12-20T00:00:00","stk_price":29.2,"em":1.48,"empct":0.048},{"stock":"pep","expiry":"2024-11-08T00:00:00","stk_price":165.96,"em":5.07,"empct":0.029},{"stock":"pep","expiry":"2024-11-15T00:00:00","stk_price":165.96,"em":6.3,"empct":0.036},{"stock":"pep","expiry":"2024-11-22T00:00:00","stk_price":165.96,"em":3.45,"empct":0.02},{"stock":"pep","expiry":"2024-11-29T00:00:00","stk_price":165.96,"em":4.15,"empct":0.024},{"stock":"pep","expiry":"2024-12-06T00:00:00","stk_price":165.96,"em":4.23,"empct":0.024},{"stock":"pep","expiry":"2024-12-20T00:00:00","stk_price":165.96,"em":4.9,"empct":0.028},{"stock":"goog","expiry":"2024-11-08T00:00:00","stk_price":171.09,"em":6.08,"empct":0.034},{"stock":"goog","expiry":"2024-11-15T00:00:00","stk_price":171.09,"em":8.11,"empct":0.045},{"stock":"goog","expiry":"2024-11-22T00:00:00","stk_price":171.09,"em":5.0,"empct":0.028},{"stock":"goog","expiry":"2024-11-29T00:00:00","stk_price":171.09,"em":5.5,"empct":0.031},{"stock":"goog","expiry":"2024-12-06T00:00:00","stk_price":171.09,"em":6.03,"empct":0.033},{"stock":"goog","expiry":"2024-12-13T00:00:00","stk_price":171.09,"em":5.95,"empct":0.033},{"stock":"goog","expiry":"2024-12-20T00:00:00","stk_price":171.09,"em":7.28,"empct":0.04},{"stock":"mmm","expiry":"2024-11-08T00:00:00","stk_price":126.28,"em":4.07,"empct":0.031},{"stock":"mmm","expiry":"2024-11-15T00:00:00","stk_price":126.28,"em":5.71,"empct":0.043},{"stock":"mmm","expiry":"2024-11-22T00:00:00","stk_price":126.28,"em":6.82,"empct":0.051},{"stock":"mmm","expiry":"2024-11-29T00:00:00","stk_price":126.28,"em":9.04,"empct":0.068},{"stock":"mmm","expiry":"2024-12-06T00:00:00","stk_price":126.28,"em":8.48,"empct":0.064},{"stock":"mmm","expiry":"2024-12-13T00:00:00","stk_price":126.28,"em":4.08,"empct":0.031},{"stock":"ntr","expiry":"2024-11-08T00:00:00","stk_price":50.61,"em":1.81,"empct":0.034},{"stock":"ntr","expiry":"2024-11-15T00:00:00","stk_price":50.61,"em":3.93,"empct":0.074},{"stock":"ntr","expiry":"2024-11-22T00:00:00","stk_price":50.61,"em":2.45,"empct":0.046},{"stock":"ntr","expiry":"2024-11-29T00:00:00","stk_price":50.61,"em":1.14,"empct":0.021},{"stock":"ntr","expiry":"2024-12-06T00:00:00","stk_price":50.61,"em":1.5,"empct":0.028},{"stock":"ntr","expiry":"2024-12-13T00:00:00","stk_price":50.61,"em":3.0,"empct":0.056},{"stock":"ntr","expiry":"2024-12-20T00:00:00","stk_price":50.61,"em":3.1,"empct":0.058},{"stock":"dkng","expiry":"2024-11-08T00:00:00","stk_price":35.77,"em":4.15,"empct":0.11},{"stock":"dkng","expiry":"2024-11-15T00:00:00","stk_price":35.77,"em":4.69,"empct":0.125},{"stock":"dkng","expiry":"2024-11-22T00:00:00","stk_price":35.77,"em":2.46,"empct":0.065},{"stock":"dkng","expiry":"2024-11-29T00:00:00","stk_price":35.77,"em":2.41,"empct":0.064},{"stock":"dkng","expiry":"2024-12-06T00:00:00","stk_price":35.77,"em":2.5,"empct":0.066},{"stock":"dkng","expiry":"2024-12-13T00:00:00","stk_price":35.77,"em":2.7,"empct":0.072},{"stock":"dkng","expiry":"2024-12-20T00:00:00","stk_price":35.77,"em":2.85,"empct":0.076},{"stock":"mdb","expiry":"2024-11-08T00:00:00","stk_price":269.33,"em":17.05,"empct":0.06},{"stock":"mdb","expiry":"2024-11-15T00:00:00","stk_price":269.33,"em":22.6,"empct":0.08},{"stock":"mdb","expiry":"2024-11-22T00:00:00","stk_price":269.33,"em":12.0,"empct":0.042},{"stock":"mdb","expiry":"2024-11-29T00:00:00","stk_price":269.33,"em":15.1,"empct":0.053},{"stock":"mdb","expiry":"2024-12-06T00:00:00","stk_price":269.33,"em":14.83,"empct":0.052},{"stock":"mdb","expiry":"2024-12-13T00:00:00","stk_price":269.33,"em":21.85,"empct":0.077},{"stock":"mdb","expiry":"2024-12-20T00:00:00","stk_price":269.33,"em":24.65,"empct":0.087},{"stock":"uwmc","expiry":"2024-11-08T00:00:00","stk_price":6.42,"em":0.78,"empct":0.115},{"stock":"uwmc","expiry":"2024-11-15T00:00:00","stk_price":6.42,"em":1.14,"empct":0.169},{"stock":"uwmc","expiry":"2024-11-22T00:00:00","stk_price":6.42,"em":1.11,"empct":0.164},{"stock":"uwmc","expiry":"2024-11-29T00:00:00","stk_price":6.42,"em":1.42,"empct":0.21},{"stock":"uwmc","expiry":"2024-12-06T00:00:00","stk_price":6.42,"em":0.45,"empct":0.067},{"stock":"uwmc","expiry":"2024-12-13T00:00:00","stk_price":6.42,"em":0.6,"empct":0.089},{"stock":"uwmc","expiry":"2024-12-20T00:00:00","stk_price":6.42,"em":0.81,"empct":0.12},{"stock":"xlu","expiry":"2024-11-08T00:00:00","stk_price":77.05,"em":2.56,"empct":0.032},{"stock":"xlu","expiry":"2024-11-15T00:00:00","stk_price":77.05,"em":3.29,"empct":0.041},{"stock":"xlu","expiry":"2024-11-22T00:00:00","stk_price":77.05,"em":3.59,"empct":0.044},{"stock":"xlu","expiry":"2024-11-29T00:00:00","stk_price":77.05,"em":3.6,"empct":0.044},{"stock":"xlu","expiry":"2024-12-06T00:00:00","stk_price":77.05,"em":3.14,"empct":0.039},{"stock":"xlu","expiry":"2024-12-20T00:00:00","stk_price":77.05,"em":2.53,"empct":0.031},{"stock":"ups","expiry":"2024-11-08T00:00:00","stk_price":132.2,"em":4.2,"empct":0.03},{"stock":"ups","expiry":"2024-11-15T00:00:00","stk_price":132.2,"em":5.8,"empct":0.042},{"stock":"ups","expiry":"2024-11-22T00:00:00","stk_price":132.2,"em":8.45,"empct":0.061},{"stock":"ups","expiry":"2024-11-29T00:00:00","stk_price":132.2,"em":7.45,"empct":0.054},{"stock":"ups","expiry":"2024-12-06T00:00:00","stk_price":132.2,"em":7.01,"empct":0.05},{"stock":"pltr","expiry":"2024-11-08T00:00:00","stk_price":41.53,"em":5.96,"empct":0.136},{"stock":"pltr","expiry":"2024-11-15T00:00:00","stk_price":41.53,"em":6.31,"empct":0.144},{"stock":"pltr","expiry":"2024-11-22T00:00:00","stk_price":41.53,"em":3.4,"empct":0.078},{"stock":"pltr","expiry":"2024-11-29T00:00:00","stk_price":41.53,"em":3.44,"empct":0.079},{"stock":"pltr","expiry":"2024-12-06T00:00:00","stk_price":41.53,"em":3.6,"empct":0.082},{"stock":"pltr","expiry":"2024-12-13T00:00:00","stk_price":41.53,"em":3.85,"empct":0.088},{"stock":"pltr","expiry":"2024-12-20T00:00:00","stk_price":41.53,"em":3.95,"empct":0.09},{"stock":"sq","expiry":"2024-11-08T00:00:00","stk_price":73.16,"em":8.4,"empct":0.109},{"stock":"sq","expiry":"2024-11-15T00:00:00","stk_price":73.16,"em":9.53,"empct":0.124},{"stock":"sq","expiry":"2024-11-22T00:00:00","stk_price":73.16,"em":10.75,"empct":0.14},{"stock":"sq","expiry":"2024-11-29T00:00:00","stk_price":73.16,"em":10.5,"empct":0.136},{"stock":"sq","expiry":"2024-12-06T00:00:00","stk_price":73.16,"em":5.75,"empct":0.075},{"stock":"vxx","expiry":"2024-11-08T00:00:00","stk_price":54.39,"em":5.6,"empct":0.098},{"stock":"vxx","expiry":"2024-11-15T00:00:00","stk_price":54.39,"em":8.03,"empct":0.14},{"stock":"vxx","expiry":"2024-11-22T00:00:00","stk_price":54.39,"em":5.75,"empct":0.1},{"stock":"vxx","expiry":"2024-11-29T00:00:00","stk_price":54.39,"em":11.5,"empct":0.201},{"stock":"vxx","expiry":"2024-12-06T00:00:00","stk_price":54.39,"em":5.45,"empct":0.095},{"stock":"vxx","expiry":"2024-12-20T00:00:00","stk_price":54.39,"em":7.5,"empct":0.131},{"stock":"wmt","expiry":"2024-11-08T00:00:00","stk_price":82.57,"em":1.23,"empct":0.014},{"stock":"wmt","expiry":"2024-11-15T00:00:00","stk_price":82.57,"em":3.33,"empct":0.038},{"stock":"wmt","expiry":"2024-11-22T00:00:00","stk_price":82.57,"em":2.76,"empct":0.032},{"stock":"wmt","expiry":"2024-11-29T00:00:00","stk_price":82.57,"em":2.96,"empct":0.034},{"stock":"wmt","expiry":"2024-12-06T00:00:00","stk_price":82.57,"em":2.99,"empct":0.034},{"stock":"wmt","expiry":"2024-12-13T00:00:00","stk_price":82.57,"em":3.53,"empct":0.041},{"stock":"cvx","expiry":"2024-11-08T00:00:00","stk_price":153.54,"em":5.79,"empct":0.036},{"stock":"cvx","expiry":"2024-11-15T00:00:00","stk_price":153.54,"em":7.25,"empct":0.045},{"stock":"cvx","expiry":"2024-11-22T00:00:00","stk_price":153.54,"em":8.75,"empct":0.054},{"stock":"cvx","expiry":"2024-11-29T00:00:00","stk_price":153.54,"em":4.05,"empct":0.025},{"stock":"cvx","expiry":"2024-12-06T00:00:00","stk_price":153.54,"em":9.98,"empct":0.062},{"stock":"cvx","expiry":"2024-12-13T00:00:00","stk_price":153.54,"em":10.67,"empct":0.066},{"stock":"cvx","expiry":"2024-12-20T00:00:00","stk_price":153.54,"em":6.0,"empct":0.037},{"stock":"fcel","expiry":"2024-11-08T00:00:00","stk_price":0.37,"em":0.13,"empct":0.334},{"stock":"fcel","expiry":"2024-11-15T00:00:00","stk_price":0.37,"em":0.16,"empct":0.411},{"stock":"fcel","expiry":"2024-11-22T00:00:00","stk_price":0.37,"em":0.29,"empct":0.745},{"stock":"fcel","expiry":"2024-11-29T00:00:00","stk_price":0.37,"em":0.16,"empct":0.411},{"stock":"fcel","expiry":"2024-12-06T00:00:00","stk_price":0.37,"em":0.29,"empct":0.745},{"stock":"fcel","expiry":"2024-12-13T00:00:00","stk_price":0.37,"em":0.2,"empct":0.514},{"stock":"vale","expiry":"2024-11-08T00:00:00","stk_price":10.81,"em":0.73,"empct":0.064},{"stock":"vale","expiry":"2024-11-15T00:00:00","stk_price":10.81,"em":0.84,"empct":0.074},{"stock":"vale","expiry":"2024-11-22T00:00:00","stk_price":10.81,"em":0.81,"empct":0.071},{"stock":"vale","expiry":"2024-11-29T00:00:00","stk_price":10.81,"em":1.01,"empct":0.089},{"stock":"vale","expiry":"2024-12-06T00:00:00","stk_price":10.81,"em":1.09,"empct":0.096},{"stock":"vale","expiry":"2024-12-13T00:00:00","stk_price":10.81,"em":0.55,"empct":0.048},{"stock":"vale","expiry":"2024-12-20T00:00:00","stk_price":10.81,"em":0.56,"empct":0.049},{"stock":"mo","expiry":"2024-11-08T00:00:00","stk_price":53.67,"em":1.7,"empct":0.03},{"stock":"mo","expiry":"2024-11-15T00:00:00","stk_price":53.67,"em":2.15,"empct":0.038},{"stock":"mo","expiry":"2024-11-22T00:00:00","stk_price":53.67,"em":2.42,"empct":0.043},{"stock":"mo","expiry":"2024-11-29T00:00:00","stk_price":53.67,"em":2.61,"empct":0.046},{"stock":"mo","expiry":"2024-12-06T00:00:00","stk_price":53.67,"em":2.98,"empct":0.053},{"stock":"mo","expiry":"2024-12-13T00:00:00","stk_price":53.67,"em":2.87,"empct":0.051},{"stock":"intc","expiry":"2024-11-08T00:00:00","stk_price":22.57,"em":1.56,"empct":0.066},{"stock":"intc","expiry":"2024-11-15T00:00:00","stk_price":22.57,"em":2.07,"empct":0.087},{"stock":"intc","expiry":"2024-11-22T00:00:00","stk_price":22.57,"em":2.54,"empct":0.107},{"stock":"intc","expiry":"2024-11-29T00:00:00","stk_price":22.57,"em":2.78,"empct":0.117},{"stock":"intc","expiry":"2024-12-06T00:00:00","stk_price":22.57,"em":3.07,"empct":0.129},{"stock":"intc","expiry":"2024-12-13T00:00:00","stk_price":22.57,"em":3.19,"empct":0.134},{"stock":"intc","expiry":"2024-12-20T00:00:00","stk_price":22.57,"em":1.77,"empct":0.075},{"stock":"smh","expiry":"2024-11-08T00:00:00","stk_price":245.67,"em":10.7,"empct":0.041},{"stock":"smh","expiry":"2024-11-15T00:00:00","stk_price":245.67,"em":15.01,"empct":0.058},{"stock":"smh","expiry":"2024-11-22T00:00:00","stk_price":245.67,"em":19.06,"empct":0.074},{"stock":"smh","expiry":"2024-11-29T00:00:00","stk_price":245.67,"em":20.22,"empct":0.078},{"stock":"smh","expiry":"2024-12-06T00:00:00","stk_price":245.67,"em":26.07,"empct":0.101},{"stock":"smh","expiry":"2024-12-13T00:00:00","stk_price":245.67,"em":13.8,"empct":0.053},{"stock":"smh","expiry":"2024-12-20T00:00:00","stk_price":245.67,"em":13.55,"empct":0.052},{"stock":"mu","expiry":"2024-11-08T00:00:00","stk_price":102.09,"em":5.51,"empct":0.051},{"stock":"mu","expiry":"2024-11-15T00:00:00","stk_price":102.09,"em":7.75,"empct":0.072},{"stock":"mu","expiry":"2024-11-22T00:00:00","stk_price":102.09,"em":9.79,"empct":0.091},{"stock":"mu","expiry":"2024-11-29T00:00:00","stk_price":102.09,"em":10.44,"empct":0.097},{"stock":"mu","expiry":"2024-12-06T00:00:00","stk_price":102.09,"em":13.15,"empct":0.122},{"stock":"mu","expiry":"2024-12-13T00:00:00","stk_price":102.09,"em":15.16,"empct":0.141},{"stock":"hd","expiry":"2024-11-08T00:00:00","stk_price":395.38,"em":14.2,"empct":0.034},{"stock":"hd","expiry":"2024-11-15T00:00:00","stk_price":395.38,"em":24.85,"empct":0.06},{"stock":"hd","expiry":"2024-11-22T00:00:00","stk_price":395.38,"em":14.4,"empct":0.035},{"stock":"hd","expiry":"2024-11-29T00:00:00","stk_price":395.38,"em":14.55,"empct":0.035},{"stock":"hd","expiry":"2024-12-06T00:00:00","stk_price":395.38,"em":14.77,"empct":0.035},{"stock":"hd","expiry":"2024-12-20T00:00:00","stk_price":395.38,"em":17.25,"empct":0.041},{"stock":"shy","expiry":"2024-11-15T00:00:00","stk_price":82.11,"em":1.11,"empct":0.013},{"stock":"shy","expiry":"2024-12-20T00:00:00","stk_price":82.11,"em":1.28,"empct":0.015},{"stock":"rrc","expiry":"2024-11-15T00:00:00","stk_price":30.78,"em":1.75,"empct":0.054},{"stock":"rrc","expiry":"2024-12-20T00:00:00","stk_price":30.78,"em":3.94,"empct":0.122},{"stock":"enph","expiry":"2024-11-08T00:00:00","stk_price":87.67,"em":9.95,"empct":0.108},{"stock":"enph","expiry":"2024-11-15T00:00:00","stk_price":87.67,"em":11.9,"empct":0.129},{"stock":"enph","expiry":"2024-11-22T00:00:00","stk_price":87.67,"em":14.95,"empct":0.162},{"stock":"enph","expiry":"2024-11-29T00:00:00","stk_price":87.67,"em":13.92,"empct":0.151},{"stock":"enph","expiry":"2024-12-06T00:00:00","stk_price":87.67,"em":7.3,"empct":0.079},{"stock":"fdn","expiry":"2024-11-15T00:00:00","stk_price":222.26,"em":6.0,"empct":0.026},{"stock":"fdn","expiry":"2024-12-20T00:00:00","stk_price":222.26,"em":9.6,"empct":0.041},{"stock":"lc","expiry":"2024-11-15T00:00:00","stk_price":13.78,"em":1.65,"empct":0.114},{"stock":"lc","expiry":"2024-12-20T00:00:00","stk_price":13.78,"em":2.45,"empct":0.169},{"stock":"jks","expiry":"2024-11-15T00:00:00","stk_price":27.95,"em":5.68,"empct":0.193},{"stock":"jks","expiry":"2024-12-20T00:00:00","stk_price":27.95,"em":10.31,"empct":0.35},{"stock":"vuzi","expiry":"2024-11-15T00:00:00","stk_price":1.16,"em":1.05,"empct":0.86},{"stock":"vuzi","expiry":"2024-12-20T00:00:00","stk_price":1.16,"em":1.0,"empct":0.819},{"stock":"bno","expiry":"2024-11-15T00:00:00","stk_price":29.89,"em":2.0,"empct":0.064},{"stock":"bno","expiry":"2024-12-20T00:00:00","stk_price":29.89,"em":4.33,"empct":0.138},{"stock":"lmt","expiry":"2024-11-08T00:00:00","stk_price":543.08,"em":13.05,"empct":0.023},{"stock":"lmt","expiry":"2024-11-15T00:00:00","stk_price":543.08,"em":10.4,"empct":0.018},{"stock":"lmt","expiry":"2024-11-22T00:00:00","stk_price":543.08,"em":9.6,"empct":0.017},{"stock":"lmt","expiry":"2024-11-29T00:00:00","stk_price":543.08,"em":11.6,"empct":0.02},{"stock":"lmt","expiry":"2024-12-06T00:00:00","stk_price":543.08,"em":13.18,"empct":0.023},{"stock":"lmt","expiry":"2024-12-20T00:00:00","stk_price":543.08,"em":15.3,"empct":0.027},{"stock":"wfc","expiry":"2024-11-08T00:00:00","stk_price":63.85,"em":3.78,"empct":0.056},{"stock":"wfc","expiry":"2024-11-15T00:00:00","stk_price":63.85,"em":4.31,"empct":0.064},{"stock":"wfc","expiry":"2024-11-22T00:00:00","stk_price":63.85,"em":4.85,"empct":0.072},{"stock":"wfc","expiry":"2024-11-29T00:00:00","stk_price":63.85,"em":6.09,"empct":0.091},{"stock":"wfc","expiry":"2024-12-06T00:00:00","stk_price":63.85,"em":5.87,"empct":0.087},{"stock":"wfc","expiry":"2024-12-13T00:00:00","stk_price":63.85,"em":2.94,"empct":0.044},{"stock":"crwd","expiry":"2024-11-08T00:00:00","stk_price":302.02,"em":15.02,"empct":0.047},{"stock":"crwd","expiry":"2024-11-15T00:00:00","stk_price":302.02,"em":21.7,"empct":0.068},{"stock":"crwd","expiry":"2024-11-22T00:00:00","stk_price":302.02,"em":14.24,"empct":0.045},{"stock":"crwd","expiry":"2024-11-29T00:00:00","stk_price":302.02,"em":20.27,"empct":0.064},{"stock":"crwd","expiry":"2024-12-06T00:00:00","stk_price":302.02,"em":21.34,"empct":0.067},{"stock":"crwd","expiry":"2024-12-13T00:00:00","stk_price":302.02,"em":21.95,"empct":0.069},{"stock":"crwd","expiry":"2024-12-20T00:00:00","stk_price":302.02,"em":25.0,"empct":0.079},{"stock":"mrk","expiry":"2024-11-08T00:00:00","stk_price":101.92,"em":3.69,"empct":0.034},{"stock":"mrk","expiry":"2024-11-15T00:00:00","stk_price":101.92,"em":4.68,"empct":0.044},{"stock":"mrk","expiry":"2024-11-22T00:00:00","stk_price":101.92,"em":5.68,"empct":0.053},{"stock":"mrk","expiry":"2024-11-29T00:00:00","stk_price":101.92,"em":5.82,"empct":0.054},{"stock":"mrk","expiry":"2024-12-06T00:00:00","stk_price":101.92,"em":3.19,"empct":0.03},{"stock":"mrk","expiry":"2024-12-13T00:00:00","stk_price":101.92,"em":3.0,"empct":0.028},{"stock":"baba","expiry":"2024-11-08T00:00:00","stk_price":98.55,"em":5.1,"empct":0.049},{"stock":"baba","expiry":"2024-11-15T00:00:00","stk_price":98.55,"em":9.04,"empct":0.087},{"stock":"baba","expiry":"2024-11-22T00:00:00","stk_price":98.55,"em":9.48,"empct":0.091},{"stock":"baba","expiry":"2024-11-29T00:00:00","stk_price":98.55,"em":10.21,"empct":0.098},{"stock":"baba","expiry":"2024-12-06T00:00:00","stk_price":98.55,"em":11.2,"empct":0.108},{"stock":"baba","expiry":"2024-12-13T00:00:00","stk_price":98.55,"em":12.5,"empct":0.12},{"stock":"slv","expiry":"2024-11-06T00:00:00","stk_price":29.59,"em":1.12,"empct":0.036},{"stock":"slv","expiry":"2024-11-08T00:00:00","stk_price":29.59,"em":1.47,"empct":0.047},{"stock":"slv","expiry":"2024-11-11T00:00:00","stk_price":29.59,"em":1.55,"empct":0.05},{"stock":"slv","expiry":"2024-11-13T00:00:00","stk_price":29.59,"em":1.72,"empct":0.055},{"stock":"slv","expiry":"2024-11-15T00:00:00","stk_price":29.59,"em":1.94,"empct":0.062},{"stock":"slv","expiry":"2024-11-22T00:00:00","stk_price":29.59,"em":2.3,"empct":0.074},{"stock":"slv","expiry":"2024-11-29T00:00:00","stk_price":29.59,"em":2.51,"empct":0.081},{"stock":"slv","expiry":"2024-12-06T00:00:00","stk_price":29.59,"em":2.75,"empct":0.088},{"stock":"slv","expiry":"2024-12-13T00:00:00","stk_price":29.59,"em":2.92,"empct":0.094},{"stock":"slv","expiry":"2024-12-20T00:00:00","stk_price":29.59,"em":1.57,"empct":0.05},{"stock":"slv","expiry":"2024-12-31T00:00:00","stk_price":29.59,"em":1.66,"empct":0.053},{"stock":"qcom","expiry":"2024-11-08T00:00:00","stk_price":165.94,"em":14.86,"empct":0.085},{"stock":"qcom","expiry":"2024-11-15T00:00:00","stk_price":165.94,"em":16.59,"empct":0.095},{"stock":"qcom","expiry":"2024-11-22T00:00:00","stk_price":165.94,"em":9.65,"empct":0.055},{"stock":"qcom","expiry":"2024-11-29T00:00:00","stk_price":165.94,"em":10.15,"empct":0.058},{"stock":"qcom","expiry":"2024-12-06T00:00:00","stk_price":165.94,"em":10.5,"empct":0.06},{"stock":"qcom","expiry":"2024-12-13T00:00:00","stk_price":165.94,"em":10.58,"empct":0.061},{"stock":"qcom","expiry":"2024-12-20T00:00:00","stk_price":165.94,"em":11.85,"empct":0.068},{"stock":"tsla","expiry":"2024-11-08T00:00:00","stk_price":244.11,"em":17.16,"empct":0.067},{"stock":"tsla","expiry":"2024-11-15T00:00:00","stk_price":244.11,"em":23.2,"empct":0.09},{"stock":"tsla","expiry":"2024-11-22T00:00:00","stk_price":244.11,"em":12.55,"empct":0.049},{"stock":"tsla","expiry":"2024-11-29T00:00:00","stk_price":244.11,"em":13.75,"empct":0.054},{"stock":"tsla","expiry":"2024-12-06T00:00:00","stk_price":244.11,"em":15.3,"empct":0.06},{"stock":"tsla","expiry":"2024-12-13T00:00:00","stk_price":244.11,"em":16.41,"empct":0.064},{"stock":"tsla","expiry":"2024-12-20T00:00:00","stk_price":244.11,"em":17.9,"empct":0.07},{"stock":"sol","expiry":"2024-11-15T00:00:00","stk_price":2.52,"em":0.15,"empct":0.057},{"stock":"sol","expiry":"2024-12-20T00:00:00","stk_price":2.52,"em":0.29,"empct":0.109},{"stock":"ardx","expiry":"2024-11-15T00:00:00","stk_price":5.96,"em":0.25,"empct":0.04},{"stock":"ardx","expiry":"2024-12-20T00:00:00","stk_price":5.96,"em":0.6,"empct":0.096},{"stock":"mos","expiry":"2024-11-08T00:00:00","stk_price":28.52,"em":1.63,"empct":0.054},{"stock":"mos","expiry":"2024-11-15T00:00:00","stk_price":28.52,"em":2.64,"empct":0.088},{"stock":"qs","expiry":"2024-11-08T00:00:00","stk_price":5.09,"em":0.68,"empct":0.127},{"stock":"qs","expiry":"2024-11-15T00:00:00","stk_price":5.09,"em":0.78,"empct":0.146},{"stock":"qs","expiry":"2024-11-22T00:00:00","stk_price":5.09,"em":0.85,"empct":0.159},{"stock":"qs","expiry":"2024-11-29T00:00:00","stk_price":5.09,"em":1.01,"empct":0.189},{"stock":"qs","expiry":"2024-12-06T00:00:00","stk_price":5.09,"em":1.0,"empct":0.187},{"stock":"qs","expiry":"2024-12-13T00:00:00","stk_price":5.09,"em":1.21,"empct":0.226},{"stock":"qs","expiry":"2024-12-20T00:00:00","stk_price":5.09,"em":0.53,"empct":0.099},{"stock":"msft","expiry":"2024-11-08T00:00:00","stk_price":407.86,"em":11.3,"empct":0.026},{"stock":"msft","expiry":"2024-11-15T00:00:00","stk_price":407.86,"em":15.47,"empct":0.036},{"stock":"msft","expiry":"2024-11-22T00:00:00","stk_price":407.86,"em":9.69,"empct":0.023},{"stock":"msft","expiry":"2024-11-29T00:00:00","stk_price":407.86,"em":10.35,"empct":0.024},{"stock":"msft","expiry":"2024-12-06T00:00:00","stk_price":407.86,"em":11.58,"empct":0.027},{"stock":"msft","expiry":"2024-12-13T00:00:00","stk_price":407.86,"em":12.35,"empct":0.029},{"stock":"msft","expiry":"2024-12-20T00:00:00","stk_price":407.86,"em":13.25,"empct":0.031},{"stock":"tgt","expiry":"2024-11-08T00:00:00","stk_price":150.73,"em":6.62,"empct":0.042},{"stock":"tgt","expiry":"2024-11-15T00:00:00","stk_price":150.73,"em":8.84,"empct":0.056},{"stock":"tgt","expiry":"2024-11-22T00:00:00","stk_price":150.73,"em":7.55,"empct":0.048},{"stock":"tgt","expiry":"2024-11-29T00:00:00","stk_price":150.73,"em":8.0,"empct":0.05},{"stock":"tgt","expiry":"2024-12-06T00:00:00","stk_price":150.73,"em":9.18,"empct":0.058},{"stock":"tgt","expiry":"2024-12-13T00:00:00","stk_price":150.73,"em":8.85,"empct":0.056},{"stock":"tgt","expiry":"2024-12-20T00:00:00","stk_price":150.73,"em":9.35,"empct":0.059},{"stock":"meta","expiry":"2024-11-08T00:00:00","stk_price":561.43,"em":21.02,"empct":0.036},{"stock":"meta","expiry":"2024-11-15T00:00:00","stk_price":561.43,"em":29.0,"empct":0.049},{"stock":"meta","expiry":"2024-11-22T00:00:00","stk_price":561.43,"em":20.23,"empct":0.034},{"stock":"meta","expiry":"2024-11-29T00:00:00","stk_price":561.43,"em":22.2,"empct":0.038},{"stock":"meta","expiry":"2024-12-06T00:00:00","stk_price":561.43,"em":24.95,"empct":0.042},{"stock":"meta","expiry":"2024-12-13T00:00:00","stk_price":561.43,"em":27.3,"empct":0.046},{"stock":"meta","expiry":"2024-12-20T00:00:00","stk_price":561.43,"em":29.11,"empct":0.049},{"stock":"abbv","expiry":"2024-11-08T00:00:00","stk_price":200.96,"em":7.3,"empct":0.035},{"stock":"abbv","expiry":"2024-11-15T00:00:00","stk_price":200.96,"em":9.08,"empct":0.043},{"stock":"abbv","expiry":"2024-11-22T00:00:00","stk_price":200.96,"em":5.5,"empct":0.026},{"stock":"abbv","expiry":"2024-11-29T00:00:00","stk_price":200.96,"em":6.54,"empct":0.031},{"stock":"abbv","expiry":"2024-12-06T00:00:00","stk_price":200.96,"em":6.5,"empct":0.031},{"stock":"abbv","expiry":"2024-12-13T00:00:00","stk_price":200.96,"em":8.93,"empct":0.042},{"stock":"abbv","expiry":"2024-12-20T00:00:00","stk_price":200.96,"em":8.38,"empct":0.04},{"stock":"moo","expiry":"2024-11-15T00:00:00","stk_price":72.13,"em":3.67,"empct":0.048},{"stock":"moo","expiry":"2024-12-20T00:00:00","stk_price":72.13,"em":1.86,"empct":0.024},{"stock":"rkt","expiry":"2024-11-08T00:00:00","stk_price":16.05,"em":1.35,"empct":0.08},{"stock":"rkt","expiry":"2024-11-15T00:00:00","stk_price":16.05,"em":2.5,"empct":0.148},{"stock":"rkt","expiry":"2024-11-22T00:00:00","stk_price":16.05,"em":2.8,"empct":0.166},{"stock":"rkt","expiry":"2024-11-29T00:00:00","stk_price":16.05,"em":1.4,"empct":0.083},{"stock":"rkt","expiry":"2024-12-06T00:00:00","stk_price":16.05,"em":1.35,"empct":0.08},{"stock":"rkt","expiry":"2024-12-13T00:00:00","stk_price":16.05,"em":1.85,"empct":0.11},{"stock":"rkt","expiry":"2024-12-20T00:00:00","stk_price":16.05,"em":1.6,"empct":0.095},{"stock":"rblx","expiry":"2024-11-08T00:00:00","stk_price":50.33,"em":2.64,"empct":0.05},{"stock":"rblx","expiry":"2024-11-15T00:00:00","stk_price":50.33,"em":3.51,"empct":0.066},{"stock":"rblx","expiry":"2024-11-22T00:00:00","stk_price":50.33,"em":3.88,"empct":0.073},{"stock":"rblx","expiry":"2024-11-29T00:00:00","stk_price":50.33,"em":4.36,"empct":0.082},{"stock":"rblx","expiry":"2024-12-06T00:00:00","stk_price":50.33,"em":5.45,"empct":0.103},{"stock":"rblx","expiry":"2024-12-13T00:00:00","stk_price":50.33,"em":4.43,"empct":0.084},{"stock":"rblx","expiry":"2024-12-20T00:00:00","stk_price":50.33,"em":2.98,"empct":0.056},{"stock":"qqq","expiry":"2024-11-05T00:00:00","stk_price":487.06,"em":2.38,"empct":0.005},{"stock":"qqq","expiry":"2024-11-06T00:00:00","stk_price":487.06,"em":5.6,"empct":0.011},{"stock":"qqq","expiry":"2024-11-07T00:00:00","stk_price":487.06,"em":6.57,"empct":0.013},{"stock":"qqq","expiry":"2024-11-08T00:00:00","stk_price":487.06,"em":14.32,"empct":0.028},{"stock":"qqq","expiry":"2024-11-11T00:00:00","stk_price":487.06,"em":8.11,"empct":0.016},{"stock":"qqq","expiry":"2024-11-12T00:00:00","stk_price":487.06,"em":8.56,"empct":0.017},{"stock":"qqq","expiry":"2024-11-13T00:00:00","stk_price":487.06,"em":9.02,"empct":0.018},{"stock":"qqq","expiry":"2024-11-14T00:00:00","stk_price":487.06,"em":9.5,"empct":0.019},{"stock":"qqq","expiry":"2024-11-15T00:00:00","stk_price":487.06,"em":9.95,"empct":0.019},{"stock":"qqq","expiry":"2024-11-22T00:00:00","stk_price":487.06,"em":22.59,"empct":0.044},{"stock":"qqq","expiry":"2024-11-29T00:00:00","stk_price":487.06,"em":13.14,"empct":0.026},{"stock":"qqq","expiry":"2024-12-06T00:00:00","stk_price":487.06,"em":26.92,"empct":0.053},{"stock":"qqq","expiry":"2024-12-13T00:00:00","stk_price":487.06,"em":30.02,"empct":0.059},{"stock":"iei","expiry":"2024-11-15T00:00:00","stk_price":116.36,"em":1.98,"empct":0.016},{"stock":"iei","expiry":"2024-12-20T00:00:00","stk_price":116.36,"em":0.97,"empct":0.008},{"stock":"nflx","expiry":"2024-11-08T00:00:00","stk_price":758.09,"em":20.45,"empct":0.026},{"stock":"nflx","expiry":"2024-11-15T00:00:00","stk_price":758.09,"em":14.34,"empct":0.018},{"stock":"nflx","expiry":"2024-11-22T00:00:00","stk_price":758.09,"em":17.6,"empct":0.022},{"stock":"nflx","expiry":"2024-11-29T00:00:00","stk_price":758.09,"em":19.16,"empct":0.024},{"stock":"nflx","expiry":"2024-12-06T00:00:00","stk_price":758.09,"em":21.0,"empct":0.026},{"stock":"nflx","expiry":"2024-12-13T00:00:00","stk_price":758.09,"em":24.9,"empct":0.031},{"stock":"nflx","expiry":"2024-12-20T00:00:00","stk_price":758.09,"em":26.0,"empct":0.033},{"stock":"pbw","expiry":"2024-11-15T00:00:00","stk_price":20.68,"em":1.78,"empct":0.082},{"stock":"pbw","expiry":"2024-12-20T00:00:00","stk_price":20.68,"em":4.15,"empct":0.191},{"stock":"ccj","expiry":"2024-11-08T00:00:00","stk_price":51.53,"em":4.7,"empct":0.087},{"stock":"ccj","expiry":"2024-11-15T00:00:00","stk_price":51.53,"em":5.5,"empct":0.101},{"stock":"ccj","expiry":"2024-11-22T00:00:00","stk_price":51.53,"em":5.8,"empct":0.107},{"stock":"ccj","expiry":"2024-11-29T00:00:00","stk_price":51.53,"em":5.88,"empct":0.108},{"stock":"ccj","expiry":"2024-12-06T00:00:00","stk_price":51.53,"em":3.15,"empct":0.058},{"stock":"ccj","expiry":"2024-12-13T00:00:00","stk_price":51.53,"em":7.1,"empct":0.131},{"stock":"xme","expiry":"2024-11-15T00:00:00","stk_price":63.61,"em":3.95,"empct":0.059},{"stock":"xme","expiry":"2024-12-20T00:00:00","stk_price":63.61,"em":5.9,"empct":0.088},{"stock":"ebay","expiry":"2024-11-08T00:00:00","stk_price":60.15,"em":3.94,"empct":0.062},{"stock":"ebay","expiry":"2024-11-15T00:00:00","stk_price":60.15,"em":2.69,"empct":0.042},{"stock":"ebay","expiry":"2024-11-22T00:00:00","stk_price":60.15,"em":4.97,"empct":0.078},{"stock":"ebay","expiry":"2024-11-29T00:00:00","stk_price":60.15,"em":5.38,"empct":0.085},{"stock":"ebay","expiry":"2024-12-06T00:00:00","stk_price":60.15,"em":3.4,"empct":0.054},{"stock":"ebay","expiry":"2024-12-13T00:00:00","stk_price":60.15,"em":2.0,"empct":0.032},{"stock":"ebay","expiry":"2024-12-20T00:00:00","stk_price":60.15,"em":2.14,"empct":0.034},{"stock":"f","expiry":"2024-11-08T00:00:00","stk_price":10.36,"em":0.8,"empct":0.073},{"stock":"f","expiry":"2024-11-15T00:00:00","stk_price":10.36,"em":0.86,"empct":0.079},{"stock":"f","expiry":"2024-11-22T00:00:00","stk_price":10.36,"em":0.96,"empct":0.088},{"stock":"f","expiry":"2024-11-29T00:00:00","stk_price":10.36,"em":0.97,"empct":0.089},{"stock":"f","expiry":"2024-12-06T00:00:00","stk_price":10.36,"em":1.1,"empct":0.101},{"stock":"f","expiry":"2024-12-13T00:00:00","stk_price":10.36,"em":1.16,"empct":0.106},{"stock":"f","expiry":"2024-12-20T00:00:00","stk_price":10.36,"em":0.62,"empct":0.057},{"stock":"ief","expiry":"2024-11-08T00:00:00","stk_price":94.08,"em":1.68,"empct":0.017},{"stock":"ief","expiry":"2024-11-15T00:00:00","stk_price":94.08,"em":2.3,"empct":0.023},{"stock":"ief","expiry":"2024-11-22T00:00:00","stk_price":94.08,"em":2.04,"empct":0.021},{"stock":"ief","expiry":"2024-11-29T00:00:00","stk_price":94.08,"em":2.83,"empct":0.029},{"stock":"ief","expiry":"2024-12-06T00:00:00","stk_price":94.08,"em":1.17,"empct":0.012},{"stock":"ief","expiry":"2024-12-20T00:00:00","stk_price":94.08,"em":1.42,"empct":0.014},{"stock":"sono","expiry":"2024-11-15T00:00:00","stk_price":13.35,"em":4.33,"empct":0.308},{"stock":"sono","expiry":"2024-12-20T00:00:00","stk_price":13.35,"em":4.25,"empct":0.302},{"stock":"pypl","expiry":"2024-11-08T00:00:00","stk_price":77.97,"em":1.33,"empct":0.016},{"stock":"pypl","expiry":"2024-11-15T00:00:00","stk_price":77.97,"em":4.13,"empct":0.05},{"stock":"pypl","expiry":"2024-11-22T00:00:00","stk_price":77.97,"em":2.32,"empct":0.028},{"stock":"pypl","expiry":"2024-11-29T00:00:00","stk_price":77.97,"em":2.85,"empct":0.035},{"stock":"pypl","expiry":"2024-12-06T00:00:00","stk_price":77.97,"em":2.95,"empct":0.036},{"stock":"pypl","expiry":"2024-12-20T00:00:00","stk_price":77.97,"em":3.95,"empct":0.048},{"stock":"ibm","expiry":"2024-11-08T00:00:00","stk_price":206.45,"em":6.5,"empct":0.03},{"stock":"ibm","expiry":"2024-11-15T00:00:00","stk_price":206.45,"em":8.5,"empct":0.039},{"stock":"ibm","expiry":"2024-11-22T00:00:00","stk_price":206.45,"em":4.46,"empct":0.021},{"stock":"ibm","expiry":"2024-11-29T00:00:00","stk_price":206.45,"em":5.05,"empct":0.023},{"stock":"ibm","expiry":"2024-12-06T00:00:00","stk_price":206.45,"em":5.3,"empct":0.024},{"stock":"ibm","expiry":"2024-12-13T00:00:00","stk_price":206.45,"em":6.1,"empct":0.028},{"stock":"ibm","expiry":"2024-12-20T00:00:00","stk_price":206.45,"em":6.6,"empct":0.03},{"stock":"xly","expiry":"2024-11-08T00:00:00","stk_price":199.4,"em":6.16,"empct":0.029},{"stock":"xly","expiry":"2024-11-15T00:00:00","stk_price":199.4,"em":7.61,"empct":0.036},{"stock":"xly","expiry":"2024-11-22T00:00:00","stk_price":199.4,"em":9.23,"empct":0.044},{"stock":"xly","expiry":"2024-11-29T00:00:00","stk_price":199.4,"em":10.52,"empct":0.05},{"stock":"xly","expiry":"2024-12-06T00:00:00","stk_price":199.4,"em":4.14,"empct":0.02},{"stock":"xly","expiry":"2024-12-13T00:00:00","stk_price":199.4,"em":8.45,"empct":0.04},{"stock":"xly","expiry":"2024-12-20T00:00:00","stk_price":199.4,"em":5.7,"empct":0.027},{"stock":"xlp","expiry":"2024-11-08T00:00:00","stk_price":80.31,"em":1.48,"empct":0.018},{"stock":"xlp","expiry":"2024-11-15T00:00:00","stk_price":80.31,"em":2.35,"empct":0.028},{"stock":"xlp","expiry":"2024-11-22T00:00:00","stk_price":80.31,"em":2.71,"empct":0.032},{"stock":"xlp","expiry":"2024-11-29T00:00:00","stk_price":80.31,"em":3.44,"empct":0.041},{"stock":"xlp","expiry":"2024-12-06T00:00:00","stk_price":80.31,"em":3.15,"empct":0.037},{"stock":"xlp","expiry":"2024-12-13T00:00:00","stk_price":80.31,"em":3.29,"empct":0.039},{"stock":"xlp","expiry":"2024-12-20T00:00:00","stk_price":80.31,"em":2.11,"empct":0.025},{"stock":"amd","expiry":"2024-11-08T00:00:00","stk_price":141.49,"em":6.69,"empct":0.045},{"stock":"amd","expiry":"2024-11-15T00:00:00","stk_price":141.49,"em":9.63,"empct":0.065},{"stock":"amc","expiry":"2024-11-08T00:00:00","stk_price":4.38,"em":0.71,"empct":0.154},{"stock":"amc","expiry":"2024-11-15T00:00:00","stk_price":4.38,"em":0.86,"empct":0.187},{"stock":"amc","expiry":"2024-11-22T00:00:00","stk_price":4.38,"em":0.94,"empct":0.204},{"stock":"amc","expiry":"2024-11-29T00:00:00","stk_price":4.38,"em":0.95,"empct":0.206},{"stock":"amc","expiry":"2024-12-06T00:00:00","stk_price":4.38,"em":1.1,"empct":0.239},{"stock":"amc","expiry":"2024-12-13T00:00:00","stk_price":4.38,"em":1.12,"empct":0.243},{"stock":"amc","expiry":"2024-12-20T00:00:00","stk_price":4.38,"em":1.17,"empct":0.254},{"stock":"xle","expiry":"2024-11-08T00:00:00","stk_price":89.57,"em":2.92,"empct":0.031},{"stock":"xle","expiry":"2024-11-15T00:00:00","stk_price":89.57,"em":3.7,"empct":0.039},{"stock":"xle","expiry":"2024-11-22T00:00:00","stk_price":89.57,"em":4.33,"empct":0.046},{"stock":"xle","expiry":"2024-11-29T00:00:00","stk_price":89.57,"em":4.47,"empct":0.047},{"stock":"xle","expiry":"2024-12-06T00:00:00","stk_price":89.57,"em":5.12,"empct":0.054},{"stock":"xle","expiry":"2024-12-13T00:00:00","stk_price":89.57,"em":2.46,"empct":0.026},{"stock":"xle","expiry":"2024-12-20T00:00:00","stk_price":89.57,"em":3.1,"empct":0.033},{"stock":"xle","expiry":"2024-12-31T00:00:00","stk_price":89.57,"em":3.6,"empct":0.038},{"stock":"xom","expiry":"2024-11-08T00:00:00","stk_price":118.39,"em":3.88,"empct":0.031},{"stock":"xom","expiry":"2024-11-15T00:00:00","stk_price":118.39,"em":5.26,"empct":0.042},{"stock":"xom","expiry":"2024-11-22T00:00:00","stk_price":118.39,"em":5.83,"empct":0.047},{"stock":"xom","expiry":"2024-11-29T00:00:00","stk_price":118.39,"em":7.14,"empct":0.057},{"stock":"xom","expiry":"2024-12-06T00:00:00","stk_price":118.39,"em":7.61,"empct":0.061},{"stock":"xom","expiry":"2024-12-13T00:00:00","stk_price":118.39,"em":3.55,"empct":0.028},{"stock":"xlb","expiry":"2024-11-15T00:00:00","stk_price":93.48,"em":3.36,"empct":0.034},{"stock":"xlb","expiry":"2024-12-20T00:00:00","stk_price":93.48,"em":5.34,"empct":0.054},{"stock":"xlk","expiry":"2024-11-08T00:00:00","stk_price":224.52,"em":8.51,"empct":0.036},{"stock":"xlk","expiry":"2024-11-15T00:00:00","stk_price":224.52,"em":10.85,"empct":0.046},{"stock":"xlk","expiry":"2024-11-22T00:00:00","stk_price":224.52,"em":12.9,"empct":0.055},{"stock":"xlk","expiry":"2024-11-29T00:00:00","stk_price":224.52,"em":14.36,"empct":0.061},{"stock":"xlk","expiry":"2024-12-06T00:00:00","stk_price":224.52,"em":15.74,"empct":0.067},{"stock":"xlk","expiry":"2024-12-20T00:00:00","stk_price":224.52,"em":7.73,"empct":0.033},{"stock":"xlre","expiry":"2024-11-15T00:00:00","stk_price":43.08,"em":2.07,"empct":0.046},{"stock":"xlre","expiry":"2024-12-20T00:00:00","stk_price":43.08,"em":3.12,"empct":0.069},{"stock":"xlv","expiry":"2024-11-08T00:00:00","stk_price":146.82,"em":5.0,"empct":0.032},{"stock":"xlv","expiry":"2024-11-15T00:00:00","stk_price":146.82,"em":5.1,"empct":0.033},{"stock":"xlv","expiry":"2024-11-22T00:00:00","stk_price":146.82,"em":5.14,"empct":0.033},{"stock":"xlv","expiry":"2024-11-29T00:00:00","stk_price":146.82,"em":5.92,"empct":0.038},{"stock":"xlv","expiry":"2024-12-06T00:00:00","stk_price":146.82,"em":6.54,"empct":0.042},{"stock":"xlv","expiry":"2024-12-13T00:00:00","stk_price":146.82,"em":2.16,"empct":0.014},{"stock":"xlv","expiry":"2024-12-20T00:00:00","stk_price":146.82,"em":7.47,"empct":0.048},{"stock":"bito","expiry":"2024-11-08T00:00:00","stk_price":18.23,"em":1.7,"empct":0.089},{"stock":"bito","expiry":"2024-11-15T00:00:00","stk_price":18.23,"em":2.14,"empct":0.112},{"stock":"bito","expiry":"2024-11-22T00:00:00","stk_price":18.23,"em":2.38,"empct":0.124},{"stock":"bito","expiry":"2024-11-29T00:00:00","stk_price":18.23,"em":2.81,"empct":0.146},{"stock":"bito","expiry":"2024-12-06T00:00:00","stk_price":18.23,"em":3.79,"empct":0.198},{"stock":"bito","expiry":"2024-12-20T00:00:00","stk_price":18.23,"em":1.59,"empct":0.083},{"stock":"bito","expiry":"2024-12-31T00:00:00","stk_price":18.23,"em":1.65,"empct":0.086},{"stock":"ibb","expiry":"2024-11-08T00:00:00","stk_price":143.05,"em":4.55,"empct":0.03},{"stock":"ibb","expiry":"2024-11-15T00:00:00","stk_price":143.05,"em":7.2,"empct":0.048},{"stock":"ibb","expiry":"2024-12-20T00:00:00","stk_price":143.05,"em":3.7,"empct":0.025},{"stock":"clsk","expiry":"2024-11-08T00:00:00","stk_price":9.84,"em":1.96,"empct":0.189},{"stock":"clsk","expiry":"2024-11-15T00:00:00","stk_price":9.84,"em":2.42,"empct":0.234},{"stock":"clsk","expiry":"2024-11-22T00:00:00","stk_price":9.84,"em":2.8,"empct":0.27},{"stock":"clsk","expiry":"2024-11-29T00:00:00","stk_price":9.84,"em":3.1,"empct":0.299},{"stock":"clsk","expiry":"2024-12-06T00:00:00","stk_price":9.84,"em":3.49,"empct":0.337},{"stock":"clsk","expiry":"2024-12-13T00:00:00","stk_price":9.84,"em":1.7,"empct":0.164},{"stock":"clsk","expiry":"2024-12-20T00:00:00","stk_price":9.84,"em":1.92,"empct":0.185},{"stock":"coin","expiry":"2024-11-08T00:00:00","stk_price":184.31,"em":21.8,"empct":0.112},{"stock":"coin","expiry":"2024-11-15T00:00:00","stk_price":184.31,"em":27.57,"empct":0.142},{"stock":"coin","expiry":"2024-11-22T00:00:00","stk_price":184.31,"em":14.5,"empct":0.075},{"stock":"coin","expiry":"2024-11-29T00:00:00","stk_price":184.31,"em":15.1,"empct":0.078},{"stock":"coin","expiry":"2024-12-06T00:00:00","stk_price":184.31,"em":16.71,"empct":0.086},{"stock":"coin","expiry":"2024-12-13T00:00:00","stk_price":184.31,"em":19.25,"empct":0.099},{"stock":"coin","expiry":"2024-12-20T00:00:00","stk_price":184.31,"em":19.7,"empct":0.102},{"stock":"lqd","expiry":"2024-11-08T00:00:00","stk_price":108.64,"em":2.12,"empct":0.019},{"stock":"lqd","expiry":"2024-11-15T00:00:00","stk_price":108.64,"em":2.13,"empct":0.019},{"stock":"lqd","expiry":"2024-11-22T00:00:00","stk_price":108.64,"em":2.85,"empct":0.025},{"stock":"lqd","expiry":"2024-11-29T00:00:00","stk_price":108.64,"em":1.28,"empct":0.011},{"stock":"lqd","expiry":"2024-12-06T00:00:00","stk_price":108.64,"em":1.45,"empct":0.013},{"stock":"lqd","expiry":"2024-12-20T00:00:00","stk_price":108.64,"em":2.14,"empct":0.019},{"stock":"asan","expiry":"2024-11-08T00:00:00","stk_price":12.56,"em":0.49,"empct":0.037},{"stock":"asan","expiry":"2024-11-15T00:00:00","stk_price":12.56,"em":1.46,"empct":0.11},{"stock":"asan","expiry":"2024-11-22T00:00:00","stk_price":12.56,"em":1.17,"empct":0.088},{"stock":"asan","expiry":"2024-11-29T00:00:00","stk_price":12.56,"em":1.17,"empct":0.088},{"stock":"asan","expiry":"2024-12-20T00:00:00","stk_price":12.56,"em":1.25,"empct":0.095},{"stock":"sbux","expiry":"2024-11-08T00:00:00","stk_price":97.0,"em":2.12,"empct":0.021},{"stock":"sbux","expiry":"2024-11-15T00:00:00","stk_price":97.0,"em":2.75,"empct":0.027},{"stock":"sbux","expiry":"2024-11-22T00:00:00","stk_price":97.0,"em":5.05,"empct":0.049},{"stock":"sbux","expiry":"2024-11-29T00:00:00","stk_price":97.0,"em":3.9,"empct":0.038},{"stock":"sbux","expiry":"2024-12-06T00:00:00","stk_price":97.0,"em":3.9,"empct":0.038},{"stock":"sbux","expiry":"2024-12-13T00:00:00","stk_price":97.0,"em":4.55,"empct":0.045},{"stock":"jets","expiry":"2024-11-08T00:00:00","stk_price":22.92,"em":1.1,"empct":0.046},{"stock":"jets","expiry":"2024-11-15T00:00:00","stk_price":22.92,"em":1.35,"empct":0.056},{"stock":"jets","expiry":"2024-11-22T00:00:00","stk_price":22.92,"em":2.64,"empct":0.109},{"stock":"jets","expiry":"2024-11-29T00:00:00","stk_price":22.92,"em":2.05,"empct":0.085},{"stock":"jets","expiry":"2024-12-06T00:00:00","stk_price":22.92,"em":1.6,"empct":0.066},{"stock":"jets","expiry":"2024-12-20T00:00:00","stk_price":22.92,"em":0.85,"empct":0.035},{"stock":"tlt","expiry":"2024-11-06T00:00:00","stk_price":91.97,"em":2.73,"empct":0.028},{"stock":"tlt","expiry":"2024-11-08T00:00:00","stk_price":91.97,"em":3.19,"empct":0.033},{"stock":"tlt","expiry":"2024-11-11T00:00:00","stk_price":91.97,"em":3.33,"empct":0.034},{"stock":"tlt","expiry":"2024-11-13T00:00:00","stk_price":91.97,"em":1.6,"empct":0.017},{"stock":"tlt","expiry":"2024-11-15T00:00:00","stk_price":91.97,"em":3.99,"empct":0.041},{"stock":"tlt","expiry":"2024-11-22T00:00:00","stk_price":91.97,"em":4.21,"empct":0.043},{"stock":"tlt","expiry":"2024-11-29T00:00:00","stk_price":91.97,"em":4.3,"empct":0.044},{"stock":"tlt","expiry":"2024-12-06T00:00:00","stk_price":91.97,"em":4.88,"empct":0.05},{"stock":"tlt","expiry":"2024-12-13T00:00:00","stk_price":91.97,"em":4.89,"empct":0.051},{"stock":"tlt","expiry":"2024-12-20T00:00:00","stk_price":91.97,"em":2.39,"empct":0.025},{"stock":"tlt","expiry":"2024-12-31T00:00:00","stk_price":91.97,"em":2.68,"empct":0.028},{"stock":"xlc","expiry":"2024-11-08T00:00:00","stk_price":92.08,"em":2.49,"empct":0.026},{"stock":"xlc","expiry":"2024-11-15T00:00:00","stk_price":92.08,"em":3.25,"empct":0.034},{"stock":"xlc","expiry":"2024-11-22T00:00:00","stk_price":92.08,"em":1.6,"empct":0.017},{"stock":"xlc","expiry":"2024-11-29T00:00:00","stk_price":92.08,"em":1.7,"empct":0.018},{"stock":"xlc","expiry":"2024-12-06T00:00:00","stk_price":92.08,"em":2.2,"empct":0.023},{"stock":"xlc","expiry":"2024-12-20T00:00:00","stk_price":92.08,"em":3.07,"empct":0.032},{"stock":"hsbc","expiry":"2024-11-08T00:00:00","stk_price":46.76,"em":1.54,"empct":0.031},{"stock":"hsbc","expiry":"2024-11-15T00:00:00","stk_price":46.76,"em":2.75,"empct":0.056},{"stock":"hsbc","expiry":"2024-11-22T00:00:00","stk_price":46.76,"em":1.2,"empct":0.024},{"stock":"hsbc","expiry":"2024-11-29T00:00:00","stk_price":46.76,"em":1.51,"empct":0.031},{"stock":"hsbc","expiry":"2024-12-06T00:00:00","stk_price":46.76,"em":1.77,"empct":0.036},{"stock":"hsbc","expiry":"2024-12-13T00:00:00","stk_price":46.76,"em":1.3,"empct":0.026},{"stock":"hsbc","expiry":"2024-12-20T00:00:00","stk_price":46.76,"em":3.25,"empct":0.066},{"stock":"kr","expiry":"2024-11-08T00:00:00","stk_price":56.24,"em":2.06,"empct":0.035},{"stock":"kr","expiry":"2024-11-15T00:00:00","stk_price":56.24,"em":2.94,"empct":0.05},{"stock":"kr","expiry":"2024-11-22T00:00:00","stk_price":56.24,"em":3.68,"empct":0.062},{"stock":"kr","expiry":"2024-11-29T00:00:00","stk_price":56.24,"em":3.44,"empct":0.058},{"stock":"kr","expiry":"2024-12-06T00:00:00","stk_price":56.24,"em":2.2,"empct":0.037},{"stock":"rtx","expiry":"2024-11-08T00:00:00","stk_price":118.11,"em":3.38,"empct":0.027},{"stock":"rtx","expiry":"2024-11-15T00:00:00","stk_price":118.11,"em":4.72,"empct":0.038},{"stock":"rtx","expiry":"2024-11-22T00:00:00","stk_price":118.11,"em":5.95,"empct":0.048},{"stock":"rtx","expiry":"2024-11-29T00:00:00","stk_price":118.11,"em":5.96,"empct":0.048},{"stock":"rtx","expiry":"2024-12-06T00:00:00","stk_price":118.11,"em":3.55,"empct":0.029},{"stock":"rtx","expiry":"2024-12-13T00:00:00","stk_price":118.11,"em":3.03,"empct":0.024},{"stock":"afrm","expiry":"2024-11-08T00:00:00","stk_price":43.54,"em":7.8,"empct":0.17},{"stock":"afrm","expiry":"2024-11-15T00:00:00","stk_price":43.54,"em":8.75,"empct":0.191},{"stock":"afrm","expiry":"2024-11-22T00:00:00","stk_price":43.54,"em":4.55,"empct":0.099},{"stock":"afrm","expiry":"2024-11-29T00:00:00","stk_price":43.54,"em":4.7,"empct":0.103},{"stock":"afrm","expiry":"2024-12-06T00:00:00","stk_price":43.54,"em":5.05,"empct":0.11},{"stock":"gsl","expiry":"2024-11-15T00:00:00","stk_price":24.17,"em":2.0,"empct":0.079},{"stock":"gsl","expiry":"2024-12-20T00:00:00","stk_price":24.17,"em":3.75,"empct":0.147},{"stock":"wba","expiry":"2024-11-08T00:00:00","stk_price":9.4,"em":0.82,"empct":0.083},{"stock":"wba","expiry":"2024-11-15T00:00:00","stk_price":9.4,"em":0.99,"empct":0.1},{"stock":"wba","expiry":"2024-11-22T00:00:00","stk_price":9.4,"em":1.21,"empct":0.122},{"stock":"wba","expiry":"2024-11-29T00:00:00","stk_price":9.4,"em":1.3,"empct":0.131},{"stock":"wba","expiry":"2024-12-06T00:00:00","stk_price":9.4,"em":1.46,"empct":0.148},{"stock":"wba","expiry":"2024-12-13T00:00:00","stk_price":9.4,"em":1.52,"empct":0.154},{"stock":"ung","expiry":"2024-11-06T00:00:00","stk_price":13.07,"em":0.8,"empct":0.058},{"stock":"ung","expiry":"2024-11-08T00:00:00","stk_price":13.07,"em":1.02,"empct":0.074},{"stock":"ung","expiry":"2024-11-13T00:00:00","stk_price":13.07,"em":0.49,"empct":0.036},{"stock":"ung","expiry":"2024-11-15T00:00:00","stk_price":13.07,"em":1.86,"empct":0.135},{"stock":"ung","expiry":"2024-11-22T00:00:00","stk_price":13.07,"em":1.89,"empct":0.137},{"stock":"ung","expiry":"2024-11-29T00:00:00","stk_price":13.07,"em":2.02,"empct":0.147},{"stock":"ung","expiry":"2024-12-06T00:00:00","stk_price":13.07,"em":2.54,"empct":0.185},{"stock":"ung","expiry":"2024-12-13T00:00:00","stk_price":13.07,"em":2.78,"empct":0.202},{"stock":"ung","expiry":"2024-12-20T00:00:00","stk_price":13.07,"em":1.22,"empct":0.089},{"stock":"ba","expiry":"2024-11-08T00:00:00","stk_price":155.65,"em":8.05,"empct":0.049},{"stock":"ba","expiry":"2024-11-15T00:00:00","stk_price":155.65,"em":11.13,"empct":0.068},{"stock":"ba","expiry":"2024-11-22T00:00:00","stk_price":155.65,"em":6.5,"empct":0.04},{"stock":"ba","expiry":"2024-11-29T00:00:00","stk_price":155.65,"em":7.25,"empct":0.044},{"stock":"ba","expiry":"2024-12-06T00:00:00","stk_price":155.65,"em":8.05,"empct":0.049},{"stock":"ba","expiry":"2024-12-13T00:00:00","stk_price":155.65,"em":8.9,"empct":0.054},{"stock":"ba","expiry":"2024-12-20T00:00:00","stk_price":155.65,"em":9.7,"empct":0.059},{"stock":"cmre","expiry":"2024-11-15T00:00:00","stk_price":13.89,"em":0.45,"empct":0.031},{"stock":"cmre","expiry":"2024-12-20T00:00:00","stk_price":13.89,"em":1.88,"empct":0.129},{"stock":"ge","expiry":"2024-11-08T00:00:00","stk_price":172.21,"em":7.2,"empct":0.04},{"stock":"ge","expiry":"2024-11-15T00:00:00","stk_price":172.21,"em":9.7,"empct":0.054},{"stock":"ge","expiry":"2024-11-22T00:00:00","stk_price":172.21,"em":6.68,"empct":0.037},{"stock":"ge","expiry":"2024-11-29T00:00:00","stk_price":172.21,"em":6.98,"empct":0.039},{"stock":"ge","expiry":"2024-12-06T00:00:00","stk_price":172.21,"em":9.7,"empct":0.054},{"stock":"ge","expiry":"2024-12-20T00:00:00","stk_price":172.21,"em":9.3,"empct":0.051},{"stock":"xrt","expiry":"2024-11-08T00:00:00","stk_price":76.15,"em":3.11,"empct":0.039},{"stock":"xrt","expiry":"2024-11-15T00:00:00","stk_price":76.15,"em":3.78,"empct":0.047},{"stock":"xrt","expiry":"2024-11-22T00:00:00","stk_price":76.15,"em":4.16,"empct":0.052},{"stock":"xrt","expiry":"2024-11-29T00:00:00","stk_price":76.15,"em":1.97,"empct":0.025},{"stock":"xrt","expiry":"2024-12-20T00:00:00","stk_price":76.15,"em":2.71,"empct":0.034},{"stock":"intu","expiry":"2024-11-08T00:00:00","stk_price":619.98,"em":24.0,"empct":0.037},{"stock":"intu","expiry":"2024-11-15T00:00:00","stk_price":619.98,"em":32.85,"empct":0.05},{"stock":"intu","expiry":"2024-11-22T00:00:00","stk_price":619.98,"em":17.7,"empct":0.027},{"stock":"intu","expiry":"2024-11-29T00:00:00","stk_price":619.98,"em":22.9,"empct":0.035},{"stock":"intu","expiry":"2024-12-20T00:00:00","stk_price":619.98,"em":27.5,"empct":0.042},{"stock":"snap","expiry":"2024-11-08T00:00:00","stk_price":12.16,"em":1.11,"empct":0.087},{"stock":"snap","expiry":"2024-11-15T00:00:00","stk_price":12.16,"em":1.39,"empct":0.109},{"stock":"snap","expiry":"2024-11-22T00:00:00","stk_price":12.16,"em":1.63,"empct":0.127},{"stock":"snap","expiry":"2024-11-29T00:00:00","stk_price":12.16,"em":1.74,"empct":0.136},{"stock":"snap","expiry":"2024-12-06T00:00:00","stk_price":12.16,"em":1.97,"empct":0.154},{"stock":"snap","expiry":"2024-12-13T00:00:00","stk_price":12.16,"em":2.1,"empct":0.164},{"stock":"snap","expiry":"2024-12-20T00:00:00","stk_price":12.16,"em":1.1,"empct":0.086},{"stock":"nvda","expiry":"2024-11-08T00:00:00","stk_price":137.54,"em":6.85,"empct":0.047},{"stock":"nvda","expiry":"2024-11-15T00:00:00","stk_price":137.54,"em":9.78,"empct":0.068},{"stock":"nvda","expiry":"2024-11-22T00:00:00","stk_price":137.54,"em":16.84,"empct":0.116},{"stock":"nvda","expiry":"2024-11-29T00:00:00","stk_price":137.54,"em":18.07,"empct":0.125},{"stock":"nvda","expiry":"2024-12-06T00:00:00","stk_price":137.54,"em":19.35,"empct":0.134},{"stock":"nvda","expiry":"2024-12-13T00:00:00","stk_price":137.54,"em":20.83,"empct":0.144},{"stock":"nvda","expiry":"2024-12-20T00:00:00","stk_price":137.54,"em":10.35,"empct":0.071},{"stock":"ctva","expiry":"2024-11-15T00:00:00","stk_price":61.18,"em":7.2,"empct":0.112},{"stock":"ctva","expiry":"2024-12-20T00:00:00","stk_price":61.18,"em":11.46,"empct":0.178},{"stock":"corn","expiry":"2024-11-15T00:00:00","stk_price":17.95,"em":1.35,"empct":0.071},{"stock":"corn","expiry":"2024-12-20T00:00:00","stk_price":17.95,"em":1.17,"empct":0.062},{"stock":"aa","expiry":"2024-11-08T00:00:00","stk_price":40.99,"em":2.69,"empct":0.062},{"stock":"aa","expiry":"2024-11-15T00:00:00","stk_price":40.99,"em":3.75,"empct":0.087},{"stock":"aa","expiry":"2024-11-22T00:00:00","stk_price":40.99,"em":2.0,"empct":0.046},{"stock":"aa","expiry":"2024-11-29T00:00:00","stk_price":40.99,"em":2.22,"empct":0.051},{"stock":"dis","expiry":"2024-11-08T00:00:00","stk_price":95.51,"em":3.37,"empct":0.034},{"stock":"dis","expiry":"2024-11-15T00:00:00","stk_price":95.51,"em":8.43,"empct":0.084},{"stock":"dis","expiry":"2024-11-22T00:00:00","stk_price":95.51,"em":8.99,"empct":0.089},{"stock":"dis","expiry":"2024-11-29T00:00:00","stk_price":95.51,"em":9.3,"empct":0.093},{"stock":"dis","expiry":"2024-12-06T00:00:00","stk_price":95.51,"em":9.6,"empct":0.095},{"stock":"dis","expiry":"2024-12-13T00:00:00","stk_price":95.51,"em":10.0,"empct":0.099},{"stock":"dis","expiry":"2024-12-20T00:00:00","stk_price":95.51,"em":5.55,"empct":0.055},{"stock":"csco","expiry":"2024-11-08T00:00:00","stk_price":55.75,"em":1.84,"empct":0.031},{"stock":"csco","expiry":"2024-11-15T00:00:00","stk_price":55.75,"em":4.09,"empct":0.07},{"stock":"csco","expiry":"2024-11-22T00:00:00","stk_price":55.75,"em":4.22,"empct":0.072},{"stock":"csco","expiry":"2024-11-29T00:00:00","stk_price":55.75,"em":4.01,"empct":0.068},{"stock":"csco","expiry":"2024-12-06T00:00:00","stk_price":55.75,"em":4.54,"empct":0.077},{"stock":"csco","expiry":"2024-12-13T00:00:00","stk_price":55.75,"em":2.55,"empct":0.043},{"stock":"csco","expiry":"2024-12-20T00:00:00","stk_price":55.75,"em":2.83,"empct":0.048},{"stock":"cvs","expiry":"2024-11-08T00:00:00","stk_price":55.04,"em":4.85,"empct":0.084},{"stock":"cvs","expiry":"2024-11-15T00:00:00","stk_price":55.04,"em":5.26,"empct":0.091},{"stock":"cvs","expiry":"2024-11-22T00:00:00","stk_price":55.04,"em":5.75,"empct":0.099},{"stock":"cvs","expiry":"2024-11-29T00:00:00","stk_price":55.04,"em":5.83,"empct":0.101},{"stock":"cvs","expiry":"2024-12-06T00:00:00","stk_price":55.04,"em":6.63,"empct":0.114},{"stock":"cvs","expiry":"2024-12-13T00:00:00","stk_price":55.04,"em":2.95,"empct":0.051},{"stock":"cvs","expiry":"2024-12-20T00:00:00","stk_price":55.04,"em":3.33,"empct":0.057},{"stock":"chgg","expiry":"2024-11-15T00:00:00","stk_price":1.69,"em":1.15,"empct":0.646},{"stock":"chgg","expiry":"2024-12-20T00:00:00","stk_price":1.69,"em":1.2,"empct":0.675},{"stock":"ko","expiry":"2024-11-08T00:00:00","stk_price":64.98,"em":1.8,"empct":0.026},{"stock":"ko","expiry":"2024-11-15T00:00:00","stk_price":64.98,"em":2.35,"empct":0.034},{"stock":"ko","expiry":"2024-11-22T00:00:00","stk_price":64.98,"em":2.81,"empct":0.041},{"stock":"ko","expiry":"2024-11-29T00:00:00","stk_price":64.98,"em":3.14,"empct":0.046},{"stock":"ko","expiry":"2024-12-06T00:00:00","stk_price":64.98,"em":3.38,"empct":0.049},{"stock":"ko","expiry":"2024-12-13T00:00:00","stk_price":64.98,"em":1.46,"empct":0.021},{"stock":"ko","expiry":"2024-12-20T00:00:00","stk_price":64.98,"em":1.63,"empct":0.024},{"stock":"icln","expiry":"2024-11-08T00:00:00","stk_price":13.47,"em":1.1,"empct":0.078},{"stock":"icln","expiry":"2024-11-15T00:00:00","stk_price":13.47,"em":1.36,"empct":0.096},{"stock":"icln","expiry":"2024-11-22T00:00:00","stk_price":13.47,"em":1.14,"empct":0.08},{"stock":"icln","expiry":"2024-11-29T00:00:00","stk_price":13.47,"em":1.16,"empct":0.082},{"stock":"icln","expiry":"2024-12-06T00:00:00","stk_price":13.47,"em":0.85,"empct":0.06},{"stock":"icln","expiry":"2024-12-13T00:00:00","stk_price":13.47,"em":1.0,"empct":0.071},{"stock":"icln","expiry":"2024-12-20T00:00:00","stk_price":13.47,"em":0.94,"empct":0.066},{"stock":"ctra","expiry":"2024-11-08T00:00:00","stk_price":23.15,"em":1.1,"empct":0.045},{"stock":"ctra","expiry":"2024-11-15T00:00:00","stk_price":23.15,"em":1.49,"empct":0.061},{"stock":"ctra","expiry":"2024-11-22T00:00:00","stk_price":23.15,"em":0.7,"empct":0.029},{"stock":"ctra","expiry":"2024-11-29T00:00:00","stk_price":23.15,"em":0.67,"empct":0.027},{"stock":"ctra","expiry":"2024-12-06T00:00:00","stk_price":23.15,"em":0.7,"empct":0.029},{"stock":"ctra","expiry":"2024-12-20T00:00:00","stk_price":23.15,"em":0.88,"empct":0.036},{"stock":"snow","expiry":"2024-11-08T00:00:00","stk_price":114.39,"em":6.65,"empct":0.055},{"stock":"snow","expiry":"2024-11-15T00:00:00","stk_price":114.39,"em":9.07,"empct":0.075},{"stock":"snow","expiry":"2024-11-22T00:00:00","stk_price":114.39,"em":16.54,"empct":0.137},{"stock":"snow","expiry":"2024-11-29T00:00:00","stk_price":114.39,"em":18.03,"empct":0.15},{"stock":"snow","expiry":"2024-12-06T00:00:00","stk_price":114.39,"em":19.3,"empct":0.16},{"stock":"snow","expiry":"2024-12-13T00:00:00","stk_price":114.39,"em":10.7,"empct":0.089},{"stock":"snow","expiry":"2024-12-20T00:00:00","stk_price":114.39,"em":10.2,"empct":0.085},{"stock":"li","expiry":"2024-11-08T00:00:00","stk_price":24.61,"em":1.8,"empct":0.069},{"stock":"li","expiry":"2024-11-15T00:00:00","stk_price":24.61,"em":2.67,"empct":0.103},{"stock":"li","expiry":"2024-11-22T00:00:00","stk_price":24.61,"em":1.55,"empct":0.06},{"stock":"li","expiry":"2024-11-29T00:00:00","stk_price":24.61,"em":1.69,"empct":0.065},{"stock":"li","expiry":"2024-12-06T00:00:00","stk_price":24.61,"em":1.7,"empct":0.066},{"stock":"li","expiry":"2024-12-20T00:00:00","stk_price":24.61,"em":2.08,"empct":0.08},{"stock":"run","expiry":"2024-11-08T00:00:00","stk_price":16.05,"em":3.34,"empct":0.198},{"stock":"run","expiry":"2024-11-15T00:00:00","stk_price":16.05,"em":3.98,"empct":0.236},{"stock":"run","expiry":"2024-11-22T00:00:00","stk_price":16.05,"em":2.01,"empct":0.119},{"stock":"run","expiry":"2024-11-29T00:00:00","stk_price":16.05,"em":2.1,"empct":0.124},{"stock":"run","expiry":"2024-12-06T00:00:00","stk_price":16.05,"em":2.21,"empct":0.131},{"stock":"run","expiry":"2024-12-20T00:00:00","stk_price":16.05,"em":2.35,"empct":0.139},{"stock":"tsn","expiry":"2024-11-15T00:00:00","stk_price":58.26,"em":5.05,"empct":0.082},{"stock":"tsn","expiry":"2024-12-20T00:00:00","stk_price":58.26,"em":6.3,"empct":0.103},{"stock":"roku","expiry":"2024-11-08T00:00:00","stk_price":67.03,"em":3.76,"empct":0.053},{"stock":"roku","expiry":"2024-11-15T00:00:00","stk_price":67.03,"em":5.11,"empct":0.072},{"stock":"roku","expiry":"2024-11-22T00:00:00","stk_price":67.03,"em":5.8,"empct":0.082},{"stock":"roku","expiry":"2024-11-29T00:00:00","stk_price":67.03,"em":6.8,"empct":0.096},{"stock":"roku","expiry":"2024-12-06T00:00:00","stk_price":67.03,"em":7.29,"empct":0.103},{"stock":"roku","expiry":"2024-12-13T00:00:00","stk_price":67.03,"em":13.11,"empct":0.186},{"stock":"iwm","expiry":"2024-11-05T00:00:00","stk_price":220.32,"em":2.56,"empct":0.011},{"stock":"iwm","expiry":"2024-11-06T00:00:00","stk_price":220.32,"em":7.41,"empct":0.032},{"stock":"iwm","expiry":"2024-11-07T00:00:00","stk_price":220.32,"em":8.72,"empct":0.038},{"stock":"iwm","expiry":"2024-11-08T00:00:00","stk_price":220.32,"em":8.96,"empct":0.039},{"stock":"iwm","expiry":"2024-11-11T00:00:00","stk_price":220.32,"em":10.09,"empct":0.044},{"stock":"iwm","expiry":"2024-11-12T00:00:00","stk_price":220.32,"em":9.7,"empct":0.042},{"stock":"iwm","expiry":"2024-11-13T00:00:00","stk_price":220.32,"em":10.74,"empct":0.046},{"stock":"iwm","expiry":"2024-11-14T00:00:00","stk_price":220.32,"em":11.91,"empct":0.051},{"stock":"iwm","expiry":"2024-11-15T00:00:00","stk_price":220.32,"em":11.0,"empct":0.047},{"stock":"iwm","expiry":"2024-11-22T00:00:00","stk_price":220.32,"em":11.96,"empct":0.052},{"stock":"iwm","expiry":"2024-11-29T00:00:00","stk_price":220.32,"em":13.11,"empct":0.057},{"stock":"iwm","expiry":"2024-12-06T00:00:00","stk_price":220.32,"em":14.42,"empct":0.062},{"stock":"iwm","expiry":"2024-12-13T00:00:00","stk_price":220.32,"em":15.63,"empct":0.067},{"stock":"iwm","expiry":"2024-12-20T00:00:00","stk_price":220.32,"em":16.45,"empct":0.071},{"stock":"iwm","expiry":"2024-12-31T00:00:00","stk_price":220.32,"em":16.97,"empct":0.073},{"stock":"lulu","expiry":"2024-11-08T00:00:00","stk_price":317.8,"em":16.3,"empct":0.049},{"stock":"lulu","expiry":"2024-11-15T00:00:00","stk_price":317.8,"em":10.85,"empct":0.032},{"stock":"lulu","expiry":"2024-11-22T00:00:00","stk_price":317.8,"em":12.58,"empct":0.038},{"stock":"lulu","expiry":"2024-11-29T00:00:00","stk_price":317.8,"em":13.75,"empct":0.041},{"stock":"lulu","expiry":"2024-12-06T00:00:00","stk_price":317.8,"em":19.58,"empct":0.059},{"stock":"lulu","expiry":"2024-12-13T00:00:00","stk_price":317.8,"em":21.01,"empct":0.063},{"stock":"lulu","expiry":"2024-12-20T00:00:00","stk_price":317.8,"em":22.2,"empct":0.066},{"stock":"itb","expiry":"2024-11-08T00:00:00","stk_price":119.07,"em":4.39,"empct":0.035},{"stock":"itb","expiry":"2024-11-15T00:00:00","stk_price":119.07,"em":3.72,"empct":0.03},{"stock":"itb","expiry":"2024-11-22T00:00:00","stk_price":119.07,"em":3.3,"empct":0.026},{"stock":"itb","expiry":"2024-12-06T00:00:00","stk_price":119.07,"em":4.4,"empct":0.035},{"stock":"oxy","expiry":"2024-11-08T00:00:00","stk_price":50.58,"em":2.36,"empct":0.044},{"stock":"oxy","expiry":"2024-11-15T00:00:00","stk_price":50.58,"em":3.73,"empct":0.07},{"stock":"oxy","expiry":"2024-11-22T00:00:00","stk_price":50.58,"em":4.37,"empct":0.082},{"stock":"oxy","expiry":"2024-11-29T00:00:00","stk_price":50.58,"em":4.56,"empct":0.086},{"stock":"oxy","expiry":"2024-12-06T00:00:00","stk_price":50.58,"em":5.05,"empct":0.095},{"stock":"oxy","expiry":"2024-12-13T00:00:00","stk_price":50.58,"em":5.42,"empct":0.102},{"stock":"oxy","expiry":"2024-12-20T00:00:00","stk_price":50.58,"em":2.88,"empct":0.054},{"stock":"tbt","expiry":"2024-11-15T00:00:00","stk_price":33.71,"em":2.78,"empct":0.078},{"stock":"tbt","expiry":"2024-12-20T00:00:00","stk_price":33.71,"em":4.17,"empct":0.118},{"stock":"c","expiry":"2024-11-08T00:00:00","stk_price":62.65,"em":1.49,"empct":0.023},{"stock":"c","expiry":"2024-11-15T00:00:00","stk_price":62.65,"em":3.83,"empct":0.058},{"stock":"c","expiry":"2024-11-22T00:00:00","stk_price":62.65,"em":2.13,"empct":0.032},{"stock":"c","expiry":"2024-11-29T00:00:00","stk_price":62.65,"em":2.2,"empct":0.033},{"stock":"c","expiry":"2024-12-06T00:00:00","stk_price":62.65,"em":2.36,"empct":0.036},{"stock":"c","expiry":"2024-12-13T00:00:00","stk_price":62.65,"em":2.81,"empct":0.043},{"stock":"c","expiry":"2024-12-20T00:00:00","stk_price":62.65,"em":3.05,"empct":0.046},{"stock":"gld","expiry":"2024-11-06T00:00:00","stk_price":252.8,"em":2.06,"empct":0.008},{"stock":"gld","expiry":"2024-11-08T00:00:00","stk_price":252.8,"em":6.03,"empct":0.023},{"stock":"gld","expiry":"2024-11-11T00:00:00","stk_price":252.8,"em":3.06,"empct":0.011},{"stock":"gld","expiry":"2024-11-13T00:00:00","stk_price":252.8,"em":3.47,"empct":0.013},{"stock":"gld","expiry":"2024-11-15T00:00:00","stk_price":252.8,"em":3.68,"empct":0.014},{"stock":"gld","expiry":"2024-11-22T00:00:00","stk_price":252.8,"em":9.07,"empct":0.034},{"stock":"gld","expiry":"2024-11-29T00:00:00","stk_price":252.8,"em":9.9,"empct":0.037},{"stock":"gld","expiry":"2024-12-06T00:00:00","stk_price":252.8,"em":10.93,"empct":0.041},{"stock":"gld","expiry":"2024-12-13T00:00:00","stk_price":252.8,"em":12.3,"empct":0.046},{"stock":"gld","expiry":"2024-12-20T00:00:00","stk_price":252.8,"em":5.8,"empct":0.022},{"stock":"lcid","expiry":"2024-11-08T00:00:00","stk_price":2.24,"em":0.63,"empct":0.267},{"stock":"lcid","expiry":"2024-11-15T00:00:00","stk_price":2.24,"em":0.75,"empct":0.318},{"stock":"lcid","expiry":"2024-11-22T00:00:00","stk_price":2.24,"em":0.77,"empct":0.327},{"stock":"lcid","expiry":"2024-11-29T00:00:00","stk_price":2.24,"em":0.81,"empct":0.344},{"stock":"lcid","expiry":"2024-12-06T00:00:00","stk_price":2.24,"em":0.82,"empct":0.348},{"stock":"lcid","expiry":"2024-12-13T00:00:00","stk_price":2.24,"em":0.9,"empct":0.382},{"stock":"lcid","expiry":"2024-12-20T00:00:00","stk_price":2.24,"em":0.98,"empct":0.416},{"stock":"weat","expiry":"2024-11-08T00:00:00","stk_price":5.11,"em":0.77,"empct":0.143},{"stock":"weat","expiry":"2024-11-15T00:00:00","stk_price":5.11,"em":0.13,"empct":0.024},{"stock":"weat","expiry":"2024-11-22T00:00:00","stk_price":5.11,"em":0.25,"empct":0.046},{"stock":"weat","expiry":"2024-11-29T00:00:00","stk_price":5.11,"em":0.05,"empct":0.009},{"stock":"weat","expiry":"2024-12-06T00:00:00","stk_price":5.11,"em":0.35,"empct":0.065},{"stock":"weat","expiry":"2024-12-20T00:00:00","stk_price":5.11,"em":0.15,"empct":0.028},{"stock":"abnb","expiry":"2024-11-08T00:00:00","stk_price":136.66,"em":12.48,"empct":0.087},{"stock":"abnb","expiry":"2024-11-15T00:00:00","stk_price":136.66,"em":13.85,"empct":0.096},{"stock":"abnb","expiry":"2024-11-22T00:00:00","stk_price":136.66,"em":14.65,"empct":0.102},{"stock":"abnb","expiry":"2024-11-29T00:00:00","stk_price":136.66,"em":15.37,"empct":0.107},{"stock":"abnb","expiry":"2024-12-06T00:00:00","stk_price":136.66,"em":15.97,"empct":0.111},{"stock":"v","expiry":"2024-11-08T00:00:00","stk_price":291.62,"em":9.9,"empct":0.032},{"stock":"v","expiry":"2024-11-15T00:00:00","stk_price":291.62,"em":11.71,"empct":0.038},{"stock":"v","expiry":"2024-11-22T00:00:00","stk_price":291.62,"em":6.96,"empct":0.023},{"stock":"v","expiry":"2024-11-29T00:00:00","stk_price":291.62,"em":7.25,"empct":0.024},{"stock":"v","expiry":"2024-12-06T00:00:00","stk_price":291.62,"em":7.8,"empct":0.025},{"stock":"v","expiry":"2024-12-20T00:00:00","stk_price":291.62,"em":9.7,"empct":0.032},{"stock":"x","expiry":"2024-11-08T00:00:00","stk_price":38.4,"em":2.41,"empct":0.06},{"stock":"x","expiry":"2024-11-15T00:00:00","stk_price":38.4,"em":4.01,"empct":0.099},{"stock":"x","expiry":"2024-11-22T00:00:00","stk_price":38.4,"em":3.07,"empct":0.076},{"stock":"x","expiry":"2024-11-29T00:00:00","stk_price":38.4,"em":3.7,"empct":0.092},{"stock":"x","expiry":"2024-12-20T00:00:00","stk_price":38.4,"em":4.93,"empct":0.122},{"stock":"mara","expiry":"2024-11-08T00:00:00","stk_price":15.62,"em":2.44,"empct":0.148},{"stock":"mara","expiry":"2024-11-15T00:00:00","stk_price":15.62,"em":3.16,"empct":0.192},{"stock":"mara","expiry":"2024-11-22T00:00:00","stk_price":15.62,"em":3.56,"empct":0.217},{"stock":"mara","expiry":"2024-11-29T00:00:00","stk_price":15.62,"em":3.91,"empct":0.238},{"stock":"mara","expiry":"2024-12-06T00:00:00","stk_price":15.62,"em":4.31,"empct":0.262},{"stock":"mara","expiry":"2024-12-13T00:00:00","stk_price":15.62,"em":4.76,"empct":0.29},{"stock":"mara","expiry":"2024-12-20T00:00:00","stk_price":15.62,"em":2.46,"empct":0.15},{"stock":"tan","expiry":"2024-11-08T00:00:00","stk_price":41.16,"em":4.3,"empct":0.099},{"stock":"tan","expiry":"2024-11-15T00:00:00","stk_price":41.16,"em":6.61,"empct":0.153},{"stock":"tan","expiry":"2024-11-22T00:00:00","stk_price":41.16,"em":2.0,"empct":0.046},{"stock":"tan","expiry":"2024-11-29T00:00:00","stk_price":41.16,"em":2.9,"empct":0.067},{"stock":"tan","expiry":"2024-12-13T00:00:00","stk_price":41.16,"em":2.55,"empct":0.059},{"stock":"tan","expiry":"2024-12-20T00:00:00","stk_price":41.16,"em":3.71,"empct":0.086},{"stock":"eog","expiry":"2024-11-08T00:00:00","stk_price":122.69,"em":3.1,"empct":0.024},{"stock":"eog","expiry":"2024-11-15T00:00:00","stk_price":122.69,"em":3.4,"empct":0.026},{"stock":"eog","expiry":"2024-11-22T00:00:00","stk_price":122.69,"em":5.0,"empct":0.039},{"stock":"eog","expiry":"2024-11-29T00:00:00","stk_price":122.69,"em":4.76,"empct":0.037},{"stock":"eog","expiry":"2024-12-06T00:00:00","stk_price":122.69,"em":5.7,"empct":0.044},{"stock":"clx","expiry":"2024-11-08T00:00:00","stk_price":162.21,"em":6.1,"empct":0.036},{"stock":"clx","expiry":"2024-11-15T00:00:00","stk_price":162.21,"em":7.39,"empct":0.043},{"stock":"clx","expiry":"2024-11-22T00:00:00","stk_price":162.21,"em":5.8,"empct":0.034},{"stock":"clx","expiry":"2024-11-29T00:00:00","stk_price":162.21,"em":5.0,"empct":0.029},{"stock":"clx","expiry":"2024-12-06T00:00:00","stk_price":162.21,"em":3.4,"empct":0.02},{"stock":"clx","expiry":"2024-12-13T00:00:00","stk_price":162.21,"em":5.68,"empct":0.033},{"stock":"clx","expiry":"2024-12-20T00:00:00","stk_price":162.21,"em":7.5,"empct":0.044},{"stock":"jpm","expiry":"2024-11-08T00:00:00","stk_price":220.21,"em":8.85,"empct":0.038},{"stock":"jpm","expiry":"2024-11-15T00:00:00","stk_price":220.21,"em":11.71,"empct":0.051},{"stock":"jpm","expiry":"2024-11-22T00:00:00","stk_price":220.21,"em":6.52,"empct":0.028},{"stock":"jpm","expiry":"2024-11-29T00:00:00","stk_price":220.21,"em":7.4,"empct":0.032},{"stock":"jpm","expiry":"2024-12-06T00:00:00","stk_price":220.21,"em":7.78,"empct":0.034},{"stock":"jpm","expiry":"2024-12-13T00:00:00","stk_price":220.21,"em":11.3,"empct":0.049},{"stock":"jpm","expiry":"2024-12-20T00:00:00","stk_price":220.21,"em":9.11,"empct":0.039},{"stock":"k","expiry":"2024-11-15T00:00:00","stk_price":80.54,"em":1.82,"empct":0.021},{"stock":"k","expiry":"2024-11-22T00:00:00","stk_price":80.54,"em":3.5,"empct":0.041},{"stock":"k","expiry":"2024-12-20T00:00:00","stk_price":80.54,"em":2.89,"empct":0.034},{"stock":"sony","expiry":"2024-11-08T00:00:00","stk_price":17.76,"em":1.11,"empct":0.059},{"stock":"sony","expiry":"2024-11-22T00:00:00","stk_price":17.76,"em":1.37,"empct":0.073},{"stock":"hood","expiry":"2024-11-08T00:00:00","stk_price":24.33,"em":1.75,"empct":0.068},{"stock":"hood","expiry":"2024-11-15T00:00:00","stk_price":24.33,"em":2.38,"empct":0.093},{"stock":"hood","expiry":"2024-11-22T00:00:00","stk_price":24.33,"em":3.07,"empct":0.12},{"stock":"hood","expiry":"2024-11-29T00:00:00","stk_price":24.33,"em":3.14,"empct":0.123},{"stock":"hood","expiry":"2024-12-06T00:00:00","stk_price":24.33,"em":3.61,"empct":0.141},{"stock":"hood","expiry":"2024-12-13T00:00:00","stk_price":24.33,"em":4.28,"empct":0.167},{"stock":"hood","expiry":"2024-12-20T00:00:00","stk_price":24.33,"em":2.2,"empct":0.086},{"stock":"pho","expiry":"2024-11-15T00:00:00","stk_price":69.13,"em":1.25,"empct":0.017},{"stock":"pho","expiry":"2024-12-20T00:00:00","stk_price":69.13,"em":5.56,"empct":0.076},{"stock":"spot","expiry":"2024-11-08T00:00:00","stk_price":380.22,"em":15.16,"empct":0.038},{"stock":"spot","expiry":"2024-11-15T00:00:00","stk_price":380.22,"em":42.14,"empct":0.105},{"stock":"spot","expiry":"2024-11-22T00:00:00","stk_price":380.22,"em":27.5,"empct":0.069},{"stock":"spot","expiry":"2024-11-29T00:00:00","stk_price":380.22,"em":23.31,"empct":0.058},{"stock":"spot","expiry":"2024-12-06T00:00:00","stk_price":380.22,"em":29.3,"empct":0.073},{"stock":"spot","expiry":"2024-12-13T00:00:00","stk_price":380.22,"em":30.4,"empct":0.076},{"stock":"spot","expiry":"2024-12-20T00:00:00","stk_price":380.22,"em":27.05,"empct":0.068},{"stock":"cag","expiry":"2024-11-08T00:00:00","stk_price":28.78,"em":1.15,"empct":0.038},{"stock":"cag","expiry":"2024-11-15T00:00:00","stk_price":28.78,"em":1.4,"empct":0.046},{"stock":"cag","expiry":"2024-11-22T00:00:00","stk_price":28.78,"em":0.65,"empct":0.021},{"stock":"cag","expiry":"2024-11-29T00:00:00","stk_price":28.78,"em":0.7,"empct":0.023},{"stock":"cag","expiry":"2024-12-06T00:00:00","stk_price":28.78,"em":0.8,"empct":0.026},{"stock":"cag","expiry":"2024-12-20T00:00:00","stk_price":28.78,"em":0.85,"empct":0.028},{"stock":"uvxy","expiry":"2024-11-08T00:00:00","stk_price":28.12,"em":4.32,"empct":0.146},{"stock":"uvxy","expiry":"2024-11-15T00:00:00","stk_price":28.12,"em":6.5,"empct":0.22},{"stock":"uvxy","expiry":"2024-11-22T00:00:00","stk_price":28.12,"em":7.45,"empct":0.252},{"stock":"uvxy","expiry":"2024-11-29T00:00:00","stk_price":28.12,"em":9.32,"empct":0.315},{"stock":"uvxy","expiry":"2024-12-06T00:00:00","stk_price":28.12,"em":8.48,"empct":0.286},{"stock":"uvxy","expiry":"2024-12-13T00:00:00","stk_price":28.12,"em":5.09,"empct":0.172},{"stock":"uvxy","expiry":"2024-12-20T00:00:00","stk_price":28.12,"em":5.4,"empct":0.182},{"stock":"bil","expiry":"2024-11-15T00:00:00","stk_price":91.5,"em":1.13,"empct":0.012},{"stock":"bil","expiry":"2024-12-20T00:00:00","stk_price":91.5,"em":1.45,"empct":0.015},{"stock":"ual","expiry":"2024-11-08T00:00:00","stk_price":77.62,"em":1.7,"empct":0.021},{"stock":"ual","expiry":"2024-11-15T00:00:00","stk_price":77.62,"em":5.5,"empct":0.067},{"stock":"ual","expiry":"2024-11-22T00:00:00","stk_price":77.62,"em":3.25,"empct":0.04},{"stock":"ual","expiry":"2024-11-29T00:00:00","stk_price":77.62,"em":3.55,"empct":0.043},{"stock":"ual","expiry":"2024-12-06T00:00:00","stk_price":77.62,"em":3.8,"empct":0.047},{"stock":"ual","expiry":"2024-12-13T00:00:00","stk_price":77.62,"em":4.22,"empct":0.052},{"stock":"ual","expiry":"2024-12-20T00:00:00","stk_price":77.62,"em":5.28,"empct":0.065},{"stock":"pgr","expiry":"2024-11-08T00:00:00","stk_price":241.65,"em":4.25,"empct":0.017},{"stock":"pgr","expiry":"2024-11-15T00:00:00","stk_price":241.65,"em":11.15,"empct":0.044},{"stock":"pgr","expiry":"2024-11-29T00:00:00","stk_price":241.65,"em":9.0,"empct":0.035},{"stock":"pgr","expiry":"2024-12-06T00:00:00","stk_price":241.65,"em":9.76,"empct":0.038},{"stock":"pgr","expiry":"2024-12-20T00:00:00","stk_price":241.65,"em":10.8,"empct":0.042},{"stock":"afl","expiry":"2024-11-08T00:00:00","stk_price":104.19,"em":4.57,"empct":0.042},{"stock":"afl","expiry":"2024-11-15T00:00:00","stk_price":104.19,"em":8.85,"empct":0.081},{"stock":"afl","expiry":"2024-11-22T00:00:00","stk_price":104.19,"em":1.2,"empct":0.011},{"stock":"afl","expiry":"2024-12-06T00:00:00","stk_price":104.19,"em":2.73,"empct":0.025},{"stock":"afl","expiry":"2024-12-13T00:00:00","stk_price":104.19,"em":3.53,"empct":0.032},{"stock":"afl","expiry":"2024-12-20T00:00:00","stk_price":104.19,"em":3.4,"empct":0.031},{"stock":"aig","expiry":"2024-11-08T00:00:00","stk_price":76.54,"em":4.6,"empct":0.057},{"stock":"aig","expiry":"2024-11-15T00:00:00","stk_price":76.54,"em":5.05,"empct":0.063},{"stock":"aig","expiry":"2024-11-22T00:00:00","stk_price":76.54,"em":5.47,"empct":0.068},{"stock":"aig","expiry":"2024-11-29T00:00:00","stk_price":76.54,"em":2.65,"empct":0.033},{"stock":"aig","expiry":"2024-12-06T00:00:00","stk_price":76.54,"em":3.3,"empct":0.041},{"stock":"kre","expiry":"2024-11-08T00:00:00","stk_price":58.19,"em":4.18,"empct":0.068},{"stock":"kre","expiry":"2024-11-15T00:00:00","stk_price":58.19,"em":4.76,"empct":0.078},{"stock":"kre","expiry":"2024-11-22T00:00:00","stk_price":58.19,"em":5.05,"empct":0.082},{"stock":"kre","expiry":"2024-11-29T00:00:00","stk_price":58.19,"em":5.24,"empct":0.086},{"stock":"kre","expiry":"2024-12-06T00:00:00","stk_price":58.19,"em":2.2,"empct":0.036},{"stock":"kre","expiry":"2024-12-20T00:00:00","stk_price":58.19,"em":3.31,"empct":0.054},{"stock":"avgo","expiry":"2024-11-08T00:00:00","stk_price":169.76,"em":3.9,"empct":0.022},{"stock":"avgo","expiry":"2024-11-15T00:00:00","stk_price":169.76,"em":12.6,"empct":0.071},{"stock":"avgo","expiry":"2024-11-22T00:00:00","stk_price":169.76,"em":6.76,"empct":0.038},{"stock":"avgo","expiry":"2024-11-29T00:00:00","stk_price":169.76,"em":7.52,"empct":0.042},{"stock":"avgo","expiry":"2024-12-06T00:00:00","stk_price":169.76,"em":8.57,"empct":0.048},{"stock":"avgo","expiry":"2024-12-13T00:00:00","stk_price":169.76,"em":10.0,"empct":0.056},{"stock":"avgo","expiry":"2024-12-20T00:00:00","stk_price":169.76,"em":23.96,"empct":0.134},{"stock":"sofi","expiry":"2024-11-08T00:00:00","stk_price":10.97,"em":0.93,"empct":0.081},{"stock":"sofi","expiry":"2024-11-15T00:00:00","stk_price":10.97,"em":1.22,"empct":0.106},{"stock":"sofi","expiry":"2024-11-22T00:00:00","stk_price":10.97,"em":1.38,"empct":0.12},{"stock":"sofi","expiry":"2024-11-29T00:00:00","stk_price":10.97,"em":1.5,"empct":0.13},{"stock":"sofi","expiry":"2024-12-06T00:00:00","stk_price":10.97,"em":1.68,"empct":0.145},{"stock":"sofi","expiry":"2024-12-13T00:00:00","stk_price":10.97,"em":1.83,"empct":0.158},{"stock":"sofi","expiry":"2024-12-20T00:00:00","stk_price":10.97,"em":0.83,"empct":0.072},{"stock":"mpw","expiry":"2024-11-08T00:00:00","stk_price":4.64,"em":0.84,"empct":0.172},{"stock":"mpw","expiry":"2024-11-15T00:00:00","stk_price":4.64,"em":0.86,"empct":0.176},{"stock":"mpw","expiry":"2024-11-22T00:00:00","stk_price":4.64,"em":0.92,"empct":0.188},{"stock":"mpw","expiry":"2024-11-29T00:00:00","stk_price":4.64,"em":0.97,"empct":0.199},{"stock":"mpw","expiry":"2024-12-06T00:00:00","stk_price":4.64,"em":1.11,"empct":0.227},{"stock":"mpw","expiry":"2024-12-13T00:00:00","stk_price":4.64,"em":1.19,"empct":0.244},{"stock":"mpw","expiry":"2024-12-20T00:00:00","stk_price":4.64,"em":1.35,"empct":0.276},{"stock":"dia","expiry":"2024-11-08T00:00:00","stk_price":418.3,"em":10.02,"empct":0.023},{"stock":"dia","expiry":"2024-11-15T00:00:00","stk_price":418.3,"em":12.57,"empct":0.029},{"stock":"dia","expiry":"2024-11-22T00:00:00","stk_price":418.3,"em":16.03,"empct":0.036},{"stock":"dia","expiry":"2024-11-29T00:00:00","stk_price":418.3,"em":13.9,"empct":0.032},{"stock":"dia","expiry":"2024-12-06T00:00:00","stk_price":418.3,"em":15.26,"empct":0.035},{"stock":"dia","expiry":"2024-12-20T00:00:00","stk_price":418.3,"em":19.95,"empct":0.045},{"stock":"arm","expiry":"2024-11-08T00:00:00","stk_price":139.47,"em":16.07,"empct":0.109},{"stock":"arm","expiry":"2024-11-15T00:00:00","stk_price":139.47,"em":19.25,"empct":0.131},{"stock":"arm","expiry":"2024-11-22T00:00:00","stk_price":139.47,"em":22.57,"empct":0.154},{"stock":"arm","expiry":"2024-11-29T00:00:00","stk_price":139.47,"em":9.65,"empct":0.066},{"stock":"arm","expiry":"2024-12-06T00:00:00","stk_price":139.47,"em":26.0,"empct":0.177},{"stock":"arm","expiry":"2024-12-13T00:00:00","stk_price":139.47,"em":12.05,"empct":0.082},{"stock":"arm","expiry":"2024-12-20T00:00:00","stk_price":139.47,"em":12.85,"empct":0.088},{"stock":"ttd","expiry":"2024-11-08T00:00:00","stk_price":119.25,"em":13.15,"empct":0.105},{"stock":"ttd","expiry":"2024-11-15T00:00:00","stk_price":119.25,"em":14.8,"empct":0.118},{"stock":"ttd","expiry":"2024-11-22T00:00:00","stk_price":119.25,"em":7.39,"empct":0.059},{"stock":"ttd","expiry":"2024-11-29T00:00:00","stk_price":119.25,"em":16.25,"empct":0.129},{"stock":"ttd","expiry":"2024-12-06T00:00:00","stk_price":119.25,"em":16.41,"empct":0.131},{"stock":"ttd","expiry":"2024-12-13T00:00:00","stk_price":119.25,"em":9.5,"empct":0.076},{"stock":"ttd","expiry":"2024-12-20T00:00:00","stk_price":119.25,"em":8.7,"empct":0.069},{"stock":"amat","expiry":"2024-11-08T00:00:00","stk_price":182.41,"em":9.35,"empct":0.049},{"stock":"amat","expiry":"2024-11-15T00:00:00","stk_price":182.41,"em":16.55,"empct":0.086},{"stock":"amat","expiry":"2024-11-22T00:00:00","stk_price":182.41,"em":12.15,"empct":0.063},{"stock":"amat","expiry":"2024-11-29T00:00:00","stk_price":182.41,"em":10.93,"empct":0.057},{"stock":"amat","expiry":"2024-12-13T00:00:00","stk_price":182.41,"em":13.65,"empct":0.071},{"stock":"amat","expiry":"2024-12-20T00:00:00","stk_price":182.41,"em":13.7,"empct":0.071},{"stock":"dash","expiry":"2024-11-08T00:00:00","stk_price":157.18,"em":7.01,"empct":0.042},{"stock":"dash","expiry":"2024-11-15T00:00:00","stk_price":157.18,"em":9.3,"empct":0.056},{"stock":"dash","expiry":"2024-11-22T00:00:00","stk_price":157.18,"em":14.85,"empct":0.09},{"stock":"dash","expiry":"2024-11-29T00:00:00","stk_price":157.18,"em":7.17,"empct":0.043},{"stock":"dash","expiry":"2024-12-06T00:00:00","stk_price":157.18,"em":6.6,"empct":0.04},{"stock":"dash","expiry":"2024-12-20T00:00:00","stk_price":157.18,"em":8.95,"empct":0.054},{"stock":"open","expiry":"2024-11-08T00:00:00","stk_price":1.85,"em":0.7,"empct":0.359},{"stock":"open","expiry":"2024-11-15T00:00:00","stk_price":1.85,"em":0.82,"empct":0.421},{"stock":"open","expiry":"2024-11-22T00:00:00","stk_price":1.85,"em":0.84,"empct":0.431},{"stock":"open","expiry":"2024-11-29T00:00:00","stk_price":1.85,"em":0.84,"empct":0.431},{"stock":"open","expiry":"2024-12-06T00:00:00","stk_price":1.85,"em":0.75,"empct":0.385},{"stock":"open","expiry":"2024-12-20T00:00:00","stk_price":1.85,"em":0.83,"empct":0.426},{"stock":"dbx","expiry":"2024-11-08T00:00:00","stk_price":26.31,"em":2.68,"empct":0.097},{"stock":"dbx","expiry":"2024-11-15T00:00:00","stk_price":26.31,"em":2.52,"empct":0.091},{"stock":"dbx","expiry":"2024-11-22T00:00:00","stk_price":26.31,"em":3.25,"empct":0.117},{"stock":"dbx","expiry":"2024-11-29T00:00:00","stk_price":26.31,"em":3.03,"empct":0.109},{"stock":"dbx","expiry":"2024-12-20T00:00:00","stk_price":26.31,"em":1.48,"empct":0.053},{"stock":"panw","expiry":"2024-11-08T00:00:00","stk_price":362.42,"em":17.75,"empct":0.047},{"stock":"panw","expiry":"2024-11-15T00:00:00","stk_price":362.42,"em":21.95,"empct":0.058},{"stock":"panw","expiry":"2024-11-22T00:00:00","stk_price":362.42,"em":22.67,"empct":0.059},{"stock":"panw","expiry":"2024-11-29T00:00:00","stk_price":362.42,"em":24.0,"empct":0.063},{"stock":"panw","expiry":"2024-12-06T00:00:00","stk_price":362.42,"em":24.75,"empct":0.065},{"stock":"panw","expiry":"2024-12-13T00:00:00","stk_price":362.42,"em":25.95,"empct":0.068},{"stock":"panw","expiry":"2024-12-20T00:00:00","stk_price":362.42,"em":26.68,"empct":0.07},{"stock":"tdoc","expiry":"2024-11-08T00:00:00","stk_price":8.97,"em":0.97,"empct":0.103},{"stock":"tdoc","expiry":"2024-11-15T00:00:00","stk_price":8.97,"em":1.08,"empct":0.114},{"stock":"tdoc","expiry":"2024-11-22T00:00:00","stk_price":8.97,"em":1.61,"empct":0.171},{"stock":"tdoc","expiry":"2024-11-29T00:00:00","stk_price":8.97,"em":1.52,"empct":0.161},{"stock":"tdoc","expiry":"2024-12-06T00:00:00","stk_price":8.97,"em":1.63,"empct":0.173},{"stock":"smci","expiry":"2024-11-08T00:00:00","stk_price":25.89,"em":6.67,"empct":0.245},{"stock":"smci","expiry":"2024-11-15T00:00:00","stk_price":25.89,"em":8.35,"empct":0.306},{"stock":"smci","expiry":"2024-11-22T00:00:00","stk_price":25.89,"em":4.5,"empct":0.165},{"stock":"smci","expiry":"2024-11-29T00:00:00","stk_price":25.89,"em":4.85,"empct":0.178},{"stock":"smci","expiry":"2024-12-06T00:00:00","stk_price":25.89,"em":5.06,"empct":0.186},{"stock":"smci","expiry":"2024-12-13T00:00:00","stk_price":25.89,"em":5.24,"empct":0.192},{"stock":"smci","expiry":"2024-12-20T00:00:00","stk_price":25.89,"em":5.52,"empct":0.203},{"stock":"hims","expiry":"2024-11-08T00:00:00","stk_price":21.12,"em":4.16,"empct":0.187},{"stock":"hims","expiry":"2024-11-15T00:00:00","stk_price":21.12,"em":4.72,"empct":0.212},{"stock":"hims","expiry":"2024-11-22T00:00:00","stk_price":21.12,"em":5.16,"empct":0.232},{"stock":"hims","expiry":"2024-11-29T00:00:00","stk_price":21.12,"em":5.32,"empct":0.239},{"stock":"hims","expiry":"2024-12-06T00:00:00","stk_price":21.12,"em":4.6,"empct":0.207},{"stock":"hims","expiry":"2024-12-13T00:00:00","stk_price":21.12,"em":2.9,"empct":0.13},{"stock":"hims","expiry":"2024-12-20T00:00:00","stk_price":21.12,"em":3.0,"empct":0.135},{"stock":"cava","expiry":"2024-11-08T00:00:00","stk_price":132.43,"em":6.32,"empct":0.045},{"stock":"cava","expiry":"2024-11-15T00:00:00","stk_price":132.43,"em":20.56,"empct":0.147},{"stock":"cava","expiry":"2024-11-22T00:00:00","stk_price":132.43,"em":22.3,"empct":0.16},{"stock":"cava","expiry":"2024-11-29T00:00:00","stk_price":132.43,"em":23.73,"empct":0.17},{"stock":"expe","expiry":"2024-11-08T00:00:00","stk_price":161.29,"em":17.05,"empct":0.1},{"stock":"expe","expiry":"2024-11-15T00:00:00","stk_price":161.29,"em":17.6,"empct":0.104},{"stock":"expe","expiry":"2024-11-22T00:00:00","stk_price":161.29,"em":20.52,"empct":0.121},{"stock":"expe","expiry":"2024-11-29T00:00:00","stk_price":161.29,"em":9.15,"empct":0.054},{"stock":"expe","expiry":"2024-12-06T00:00:00","stk_price":161.29,"em":10.0,"empct":0.059},{"stock":"expe","expiry":"2024-12-13T00:00:00","stk_price":161.29,"em":8.25,"empct":0.049},{"stock":"expe","expiry":"2024-12-20T00:00:00","stk_price":161.29,"em":9.95,"empct":0.059},{"stock":"djt","expiry":"2024-11-08T00:00:00","stk_price":33.78,"em":17.59,"empct":0.495},{"stock":"djt","expiry":"2024-11-15T00:00:00","stk_price":33.78,"em":20.05,"empct":0.564},{"stock":"djt","expiry":"2024-11-22T00:00:00","stk_price":33.78,"em":22.2,"empct":0.624},{"stock":"djt","expiry":"2024-11-29T00:00:00","stk_price":33.78,"em":22.64,"empct":0.637},{"stock":"djt","expiry":"2024-12-06T00:00:00","stk_price":33.78,"em":22.9,"empct":0.644},{"stock":"djt","expiry":"2024-12-13T00:00:00","stk_price":33.78,"em":12.2,"empct":0.343},{"stock":"djt","expiry":"2024-12-20T00:00:00","stk_price":33.78,"em":12.0,"empct":0.337},{"stock":"rddt","expiry":"2024-11-08T00:00:00","stk_price":110.14,"em":7.55,"empct":0.065},{"stock":"rddt","expiry":"2024-11-15T00:00:00","stk_price":110.14,"em":10.4,"empct":0.09},{"stock":"rddt","expiry":"2024-11-22T00:00:00","stk_price":110.14,"em":12.31,"empct":0.106},{"stock":"rddt","expiry":"2024-11-29T00:00:00","stk_price":110.14,"em":14.05,"empct":0.121},{"stock":"rddt","expiry":"2024-12-06T00:00:00","stk_price":110.14,"em":16.1,"empct":0.139},{"stock":"rddt","expiry":"2024-12-13T00:00:00","stk_price":110.14,"em":9.85,"empct":0.085},{"stock":"rddt","expiry":"2024-12-20T00:00:00","stk_price":110.14,"em":9.65,"empct":0.083},{"stock":"dell","expiry":"2024-11-08T00:00:00","stk_price":130.75,"em":8.05,"empct":0.058},{"stock":"dell","expiry":"2024-11-15T00:00:00","stk_price":130.75,"em":10.35,"empct":0.075},{"stock":"dell","expiry":"2024-11-22T00:00:00","stk_price":130.75,"em":13.01,"empct":0.095},{"stock":"dell","expiry":"2024-11-29T00:00:00","stk_price":130.75,"em":17.96,"empct":0.13},{"stock":"dell","expiry":"2024-12-06T00:00:00","stk_price":130.75,"em":19.82,"empct":0.144},{"stock":"dell","expiry":"2024-12-13T00:00:00","stk_price":130.75,"em":22.15,"empct":0.161},{"stock":"dell","expiry":"2024-12-20T00:00:00","stk_price":130.75,"em":11.57,"empct":0.084},{"stock":"fxy","expiry":"2024-11-15T00:00:00","stk_price":60.71,"em":2.13,"empct":0.033},{"stock":"fxy","expiry":"2024-12-20T00:00:00","stk_price":60.71,"em":3.15,"empct":0.049},{"stock":"dltr","expiry":"2024-11-08T00:00:00","stk_price":67.11,"em":6.08,"empct":0.086},{"stock":"dltr","expiry":"2024-11-15T00:00:00","stk_price":67.11,"em":7.65,"empct":0.108},{"stock":"dltr","expiry":"2024-11-22T00:00:00","stk_price":67.11,"em":10.14,"empct":0.144},{"stock":"dltr","expiry":"2024-11-29T00:00:00","stk_price":67.11,"em":7.97,"empct":0.113},{"stock":"dltr","expiry":"2024-12-06T00:00:00","stk_price":67.11,"em":12.96,"empct":0.183},{"stock":"dltr","expiry":"2024-12-13T00:00:00","stk_price":67.11,"em":8.44,"empct":0.119},{"stock":"adbe","expiry":"2024-11-08T00:00:00","stk_price":482.76,"em":16.4,"empct":0.032},{"stock":"adbe","expiry":"2024-11-15T00:00:00","stk_price":482.76,"em":22.05,"empct":0.043},{"stock":"adbe","expiry":"2024-11-22T00:00:00","stk_price":482.76,"em":15.02,"empct":0.03},{"stock":"adbe","expiry":"2024-11-29T00:00:00","stk_price":482.76,"em":14.43,"empct":0.028},{"stock":"adbe","expiry":"2024-12-06T00:00:00","stk_price":482.76,"em":16.35,"empct":0.032},{"stock":"adbe","expiry":"2024-12-13T00:00:00","stk_price":482.76,"em":24.85,"empct":0.049},{"stock":"adbe","expiry":"2024-12-20T00:00:00","stk_price":482.76,"em":26.0,"empct":0.051},{"stock":"orcl","expiry":"2024-11-08T00:00:00","stk_price":169.63,"em":6.76,"empct":0.038},{"stock":"orcl","expiry":"2024-11-15T00:00:00","stk_price":169.63,"em":8.75,"empct":0.049},{"stock":"orcl","expiry":"2024-11-22T00:00:00","stk_price":169.63,"em":4.56,"empct":0.026},{"stock":"orcl","expiry":"2024-11-29T00:00:00","stk_price":169.63,"em":4.95,"empct":0.028},{"stock":"orcl","expiry":"2024-12-06T00:00:00","stk_price":169.63,"em":5.25,"empct":0.029},{"stock":"orcl","expiry":"2024-12-13T00:00:00","stk_price":169.63,"em":8.14,"empct":0.046},{"stock":"orcl","expiry":"2024-12-20T00:00:00","stk_price":169.63,"em":9.0,"empct":0.05}]