[{"stock":"$NVDA","type":"\ud83d\udd34P","strike":"$130.0","exp":"09\/20\/24","gatherdate":"2024-06-12 15:07:02","contractsymbol":"NVDA240920P00130000","stk_price":125.42,"lastprice":13.85,"change":-2.6499996,"percentchange":-16.060604,"volume":3100,"openinterest":2636,"impliedvolatility":0.4320125159,"lastprice_chg":13.75,"lastprice_avg_30d":0.7443333333,"pct_chg":13750.0,"iv_chg":-0.2506078455,"iv_avg_30d":0.6216794017,"iv_avg_all":0.6143227045,"vol_chg":3050.0,"oi_chg":1064.0,"flag":1,"amnt":1014,"voi":1.0,"iv_diff":0.1896668859,"moneyness":0.9647692308},{"stock":"$NVDA","type":"\ud83d\udd34P","strike":"$120.0","exp":"09\/20\/24","gatherdate":"2024-06-12 15:07:02","contractsymbol":"NVDA240920P00120000","stk_price":125.42,"lastprice":8.8,"change":-1.8499994,"percentchange":-17.370888,"volume":1175,"openinterest":16520,"impliedvolatility":0.4436090796,"lastprice_chg":8.72,"lastprice_avg_30d":0.563,"pct_chg":10900.0,"iv_chg":-0.2390112817,"iv_avg_30d":0.6370397625,"iv_avg_all":0.6291540991,"vol_chg":1163.0,"oi_chg":14815.0,"flag":1,"amnt":14803,"voi":0.0,"iv_diff":0.1934306829,"moneyness":1.0451666667},{"stock":"$AAPL","type":"\ud83d\udfe2C","strike":"$220.0","exp":"06\/14\/24","gatherdate":"2024-06-12 14:52:55","contractsymbol":"AAPL240614C00220000","stk_price":219.45,"lastprice":2.54,"change":2.33,"percentchange":1226.3154,"volume":346798,"openinterest":16709,"impliedvolatility":0.3291082715,"lastprice_chg":2.42,"lastprice_avg_30d":0.594,"pct_chg":2016.6666666667,"iv_chg":-0.0302731348,"iv_avg_30d":0.2913156807,"iv_avg_all":0.2913156807,"vol_chg":324108.0,"oi_chg":7585.0,"flag":0,"amnt":0,"voi":20.0,"iv_diff":-0.0377925908,"moneyness":0.9975},{"stock":"$AAPL","type":"\ud83d\udfe2C","strike":"$217.5","exp":"06\/14\/24","gatherdate":"2024-06-12 14:52:55","contractsymbol":"AAPL240614C00217500","stk_price":219.45,"lastprice":3.95,"change":3.6200001,"percentchange":1034.286,"volume":206464,"openinterest":9875,"impliedvolatility":0.3501041553,"lastprice_chg":3.76,"lastprice_avg_30d":2.07,"pct_chg":1978.9473684211,"iv_chg":0.0107420801,"iv_avg_30d":0.3447331152,"iv_avg_all":0.3447331152,"vol_chg":190988.0,"oi_chg":7445.0,"flag":0,"amnt":0,"voi":20.0,"iv_diff":-0.00537104,"moneyness":1.0089655172},{"stock":"$SPY","type":"\ud83d\udfe2C","strike":"$551.0","exp":"06\/18\/24","gatherdate":"2024-06-12 14:51:56","contractsymbol":"SPY240618C00551000","stk_price":541.88,"lastprice":0.47,"change":0.36,"percentchange":327.27277,"volume":1074,"openinterest":373,"impliedvolatility":0.0998625171,"lastprice_chg":0.39,"lastprice_avg_30d":0.2233333333,"pct_chg":487.5,"iv_chg":-0.0007324146,"iv_avg_30d":0.101490105,"iv_avg_all":0.101490105,"vol_chg":1062.0,"oi_chg":59.0,"flag":1,"amnt":47,"voi":2.0,"iv_diff":0.0016275879,"moneyness":0.9834482759},{"stock":"$UBER","type":"\ud83d\udfe2C","strike":"$75.0","exp":"06\/21\/24","gatherdate":"2024-06-12 14:53:31","contractsymbol":"UBER240621C00075000","stk_price":72.61,"lastprice":0.67,"change":0.47000003,"percentchange":235.00003,"volume":2907,"openinterest":13102,"impliedvolatility":0.3325262061,"lastprice_chg":0.55,"lastprice_avg_30d":1.0206666667,"pct_chg":458.3333333333,"iv_chg":-0.0063475928,"iv_avg_30d":0.371515074,"iv_avg_all":0.4001524829,"vol_chg":2855.0,"oi_chg":3.0,"flag":0,"amnt":0,"voi":0.0,"iv_diff":0.0389888679,"moneyness":0.9681333333},{"stock":"$TTD","type":"\ud83d\udfe2C","strike":"$103.0","exp":"06\/21\/24","gatherdate":"2024-06-12 15:14:09","contractsymbol":"TTD240621C00103000","stk_price":96.44,"lastprice":0.56,"change":0.45,"percentchange":409.09085,"volume":1092,"openinterest":29,"impliedvolatility":0.3354558643,"lastprice_chg":0.45,"lastprice_avg_30d":0.5433333333,"pct_chg":409.0909090909,"iv_chg":-0.0541986768,"iv_avg_30d":0.3537051935,"iv_avg_all":0.3537051935,"vol_chg":1088.0,"oi_chg":0.0,"flag":0,"amnt":0,"voi":37.0,"iv_diff":0.0182493292,"moneyness":0.9363106796},{"stock":"$ARM","type":"\ud83d\udfe2C","strike":"$160.0","exp":"06\/14\/24","gatherdate":"2024-06-12 15:14:02","contractsymbol":"ARM240614C00160000","stk_price":157.46,"lastprice":2.58,"change":2.12,"percentchange":460.8695,"volume":11780,"openinterest":2576,"impliedvolatility":0.6450230811,"lastprice_chg":2.02,"lastprice_avg_30d":0.5772727273,"pct_chg":360.7142857143,"iv_chg":-0.1142566699,"iv_avg_30d":0.7314923868,"iv_avg_all":0.7314923868,"vol_chg":8094.0,"oi_chg":-536.0,"flag":0,"amnt":0,"voi":4.0,"iv_diff":0.0864693058,"moneyness":0.984125},{"stock":"$MU","type":"\ud83d\udfe2C","strike":"$143.0","exp":"06\/14\/24","gatherdate":"2024-06-12 14:56:29","contractsymbol":"MU240614C00143000","stk_price":140.19,"lastprice":1.05,"change":0.81999993,"percentchange":356.52167,"volume":1255,"openinterest":235,"impliedvolatility":0.4350642432,"lastprice_chg":0.82,"lastprice_avg_30d":0.4628571429,"pct_chg":356.5217391304,"iv_chg":0.0019531055,"iv_avg_30d":0.4370173486,"iv_avg_all":0.4370173486,"vol_chg":1205.0,"oi_chg":14.0,"flag":0,"amnt":0,"voi":5.0,"iv_diff":0.0019531055,"moneyness":0.9803496503},{"stock":"$MSFT","type":"\ud83d\udfe2C","strike":"$447.5","exp":"06\/14\/24","gatherdate":"2024-06-12 14:59:22","contractsymbol":"MSFT240614C00447500","stk_price":440.62,"lastprice":0.63,"change":0.39999998,"percentchange":173.91301,"volume":2273,"openinterest":1337,"impliedvolatility":0.1814046704,"lastprice_chg":0.49,"lastprice_avg_30d":0.2966666667,"pct_chg":350.0,"iv_chg":-0.0241696802,"iv_avg_30d":0.1970295142,"iv_avg_all":0.1970295142,"vol_chg":1485.0,"oi_chg":553.0,"flag":0,"amnt":0,"voi":1.0,"iv_diff":0.0156248438,"moneyness":0.9846256983},{"stock":"$HIMS","type":"\ud83d\udfe2C","strike":"$25.0","exp":"06\/21\/24","gatherdate":"2024-06-12 15:14:58","contractsymbol":"HIMS240621C00025000","stk_price":23.84,"lastprice":0.67,"change":0.43,"percentchange":204.76193,"volume":2164,"openinterest":3613,"impliedvolatility":0.7050810742,"lastprice_chg":0.52,"lastprice_avg_30d":0.3136363636,"pct_chg":346.6666666667,"iv_chg":-0.0117186328,"iv_avg_30d":0.7953678134,"iv_avg_all":0.7953678134,"vol_chg":2144.0,"oi_chg":6.0,"flag":0,"amnt":0,"voi":0.0,"iv_diff":0.0902867392,"moneyness":0.9536},{"stock":"$MSFT","type":"\ud83d\udfe2C","strike":"$445.0","exp":"06\/14\/24","gatherdate":"2024-06-12 14:59:22","contractsymbol":"MSFT240614C00445000","stk_price":440.62,"lastprice":1.1,"change":0.72,"percentchange":163.63638,"volume":16161,"openinterest":5272,"impliedvolatility":0.1748129395,"lastprice_chg":0.85,"lastprice_avg_30d":1.059047619,"pct_chg":340.0,"iv_chg":-0.0278317529,"iv_avg_30d":0.1900018222,"iv_avg_all":0.1900018222,"vol_chg":15035.0,"oi_chg":416.0,"flag":0,"amnt":0,"voi":3.0,"iv_diff":0.0151888827,"moneyness":0.9901573034},{"stock":"$CLSK","type":"\ud83d\udfe2C","strike":"$17.5","exp":"06\/14\/24","gatherdate":"2024-06-12 15:04:14","contractsymbol":"CLSK240614C00017500","stk_price":17.83,"lastprice":0.65,"change":0.46999997,"percentchange":261.11108,"volume":4805,"openinterest":3181,"impliedvolatility":0.7773459766,"lastprice_chg":0.5,"lastprice_avg_30d":0.7261538462,"pct_chg":333.3333333333,"iv_chg":-0.1953105469,"iv_avg_30d":0.9791184803,"iv_avg_all":0.9791184803,"vol_chg":2703.0,"oi_chg":-1388.0,"flag":0,"amnt":0,"voi":1.0,"iv_diff":0.2017725038,"moneyness":1.0188571429},{"stock":"$ARM","type":"\ud83d\udfe2C","strike":"$165.0","exp":"06\/14\/24","gatherdate":"2024-06-12 15:14:02","contractsymbol":"ARM240614C00165000","stk_price":157.46,"lastprice":1.4,"change":1.12,"percentchange":400.00003,"volume":2057,"openinterest":808,"impliedvolatility":0.7031279688,"lastprice_chg":1.06,"lastprice_avg_30d":0.6433333333,"pct_chg":311.7647058824,"iv_chg":-0.1142566699,"iv_avg_30d":0.7965515137,"iv_avg_all":0.7965515137,"vol_chg":948.0,"oi_chg":497.0,"flag":0,"amnt":0,"voi":2.0,"iv_diff":0.0934235449,"moneyness":0.9543030303},{"stock":"$HD","type":"\ud83d\udfe2C","strike":"$355.0","exp":"06\/14\/24","gatherdate":"2024-06-12 14:56:38","contractsymbol":"HD240614C00355000","stk_price":345.18,"lastprice":0.36,"change":0.25,"percentchange":227.2727,"volume":1851,"openinterest":136,"impliedvolatility":0.2426833545,"lastprice_chg":0.26,"lastprice_avg_30d":0.19,"pct_chg":260.0,"iv_chg":-0.081053877,"iv_avg_30d":0.2717357983,"iv_avg_all":0.2717357983,"vol_chg":1825.0,"oi_chg":19.0,"flag":0,"amnt":0,"voi":13.0,"iv_diff":0.0290524438,"moneyness":0.9723380282},{"stock":"$ITB","type":"\ud83d\udfe2C","strike":"$108.0","exp":"06\/21\/24","gatherdate":"2024-06-12 15:09:55","contractsymbol":"ITB240621C00108000","stk_price":105.32,"lastprice":0.65,"change":0.45,"percentchange":225.00002,"volume":2609,"openinterest":211,"impliedvolatility":0.2263260962,"lastprice_chg":0.45,"lastprice_avg_30d":1.05,"pct_chg":225.0,"iv_chg":-0.0432124585,"iv_avg_30d":0.2424679384,"iv_avg_all":0.2424679384,"vol_chg":2601.0,"oi_chg":-8.0,"flag":0,"amnt":0,"voi":12.0,"iv_diff":0.0161418423,"moneyness":0.9751851852},{"stock":"$TSLA","type":"\ud83d\udfe2C","strike":"$185.0","exp":"06\/14\/24","gatherdate":"2024-06-12 14:58:38","contractsymbol":"TSLA240614C00185000","stk_price":179.26,"lastprice":2.57,"change":1.7199999,"percentchange":202.35292,"volume":70447,"openinterest":55051,"impliedvolatility":0.7399928345,"lastprice_chg":1.74,"lastprice_avg_30d":3.5772222222,"pct_chg":209.6385542169,"iv_chg":0.0148924292,"iv_avg_30d":0.51288668,"iv_avg_all":0.51288668,"vol_chg":2480.0,"oi_chg":5526.0,"flag":0,"amnt":0,"voi":1.0,"iv_diff":-0.2271061545,"moneyness":0.968972973},{"stock":"$TSLA","type":"\ud83d\udfe2C","strike":"$182.5","exp":"06\/14\/24","gatherdate":"2024-06-12 14:58:38","contractsymbol":"TSLA240614C00182500","stk_price":179.26,"lastprice":3.4,"change":2.27,"percentchange":200.88493,"volume":27538,"openinterest":0,"impliedvolatility":0.740725249,"lastprice_chg":2.25,"lastprice_avg_30d":3.515,"pct_chg":195.652173913,"iv_chg":0.0224607129,"iv_avg_30d":0.5605146488,"iv_avg_all":0.5605146488,"vol_chg":14063.0,"oi_chg":-16268.0,"flag":0,"amnt":0,"voi":null,"iv_diff":-0.1802106002,"moneyness":0.9822465753},{"stock":"$TLT","type":"\ud83d\udfe2C","strike":"$92.0","exp":"06\/12\/24","gatherdate":"2024-06-12 15:05:02","contractsymbol":"TLT240612C00092000","stk_price":93.01,"lastprice":1.06,"change":0.5899999,"percentchange":125.53189,"volume":2830,"openinterest":9344,"impliedvolatility":0.2294998926,"lastprice_chg":0.64,"lastprice_avg_30d":0.7190909091,"pct_chg":152.380952381,"iv_chg":0.0263669238,"iv_avg_30d":0.1677107377,"iv_avg_all":0.1677107377,"vol_chg":-2834.0,"oi_chg":5167.0,"flag":0,"amnt":0,"voi":0.0,"iv_diff":-0.0617891548,"moneyness":1.0109782609},{"stock":"$PYPL","type":"\ud83d\udd34P","strike":"$63.0","exp":"06\/14\/24","gatherdate":"2024-06-12 15:02:15","contractsymbol":"PYPL240614P00063000","stk_price":63.48,"lastprice":0.54,"change":0.27,"percentchange":117.39132,"volume":1639,"openinterest":2343,"impliedvolatility":0.3530338135,"lastprice_chg":0.3,"lastprice_avg_30d":1.3836,"pct_chg":125.0,"iv_chg":0.0278317529,"iv_avg_30d":0.283766928,"iv_avg_all":0.283766928,"vol_chg":276.0,"oi_chg":621.0,"flag":0,"amnt":0,"voi":0.0,"iv_diff":-0.0692668854,"moneyness":1.0076190476},{"stock":"$BITO","type":"\ud83d\udfe2C","strike":"$25.5","exp":"06\/14\/24","gatherdate":"2024-06-12 15:03:59","contractsymbol":"BITO240614C00025500","stk_price":26.05,"lastprice":0.87,"change":0.35000002,"percentchange":67.3077,"volume":1398,"openinterest":1191,"impliedvolatility":0.4492242578,"lastprice_chg":0.46,"lastprice_avg_30d":1.33625,"pct_chg":112.1951219512,"iv_chg":-0.0449214258,"iv_avg_30d":0.5127001855,"iv_avg_all":0.5127001855,"vol_chg":83.0,"oi_chg":862.0,"flag":0,"amnt":0,"voi":1.0,"iv_diff":0.0634759277,"moneyness":1.0215686275},{"stock":"$CCJ","type":"\ud83d\udfe2C","strike":"$54.0","exp":"06\/14\/24","gatherdate":"2024-06-12 15:01:33","contractsymbol":"CCJ240614C00054000","stk_price":52.49,"lastprice":0.27,"change":0.17000002,"percentchange":170.00003,"volume":1170,"openinterest":939,"impliedvolatility":0.4140683594,"lastprice_chg":0.14,"lastprice_avg_30d":1.4364705882,"pct_chg":107.6923076923,"iv_chg":-0.0546869531,"iv_avg_30d":0.4277688198,"iv_avg_all":0.4277688198,"vol_chg":772.0,"oi_chg":-105.0,"flag":0,"amnt":0,"voi":1.0,"iv_diff":0.0137004604,"moneyness":0.972037037}]